Workbook
Name Circ: Cover!$G$9

Sheet Cover
E5: SaaS Financial Model
E9: Circ | G9: 1
E11: Today | G11: =NOW() -> 46271.399
E12: Date | G12: =G11 -> 46271.399
E13: Last Modified | G13: MB
E15: Legend
E17: Hardcode
E18: Sheet Link
E19: Same Sheet Reference
E20: Calculation

Sheet Metrics Dashboard
C3: Runway Month | E3: ='Detailed Financials'!G197 -> 11
C4: Runway Date | E4: ='Detailed Financials'!G198 -> 45597
C5: Funding Needed | E5: ='Detailed Financials'!G193 -> 21399064
G9: Blended / Total | N9: Monthly Subscribers | U9: Annual Subscribers
G10: 45627 | H10: =EDATE(G10,12) -> 45992 | I10: =EDATE(H10,12) -> 46357 | J10: =EDATE(I10,12) -> 46722 | K10: =EDATE(J10,12) -> 47088 | N10: 45627 | O10: =EDATE(N10,12) -> 45992 | P10: =EDATE(O10,12) -> 46357 | Q10: =EDATE(P10,12) -> 46722 | R10: =EDATE(Q10,12) -> 47088 | U10: 45627 | V10: =EDATE(U10,12) -> 45992 | W10: =EDATE(V10,12) -> 46357 | X10: =EDATE(W10,12) -> 46722 | Y10: =EDATE(X10,12) -> 47088
C12: Active Subscribers | G12: =N12+U12 -> 2063 | H12: =O12+V12 -> 6400 | I12: =P12+W12 -> 18221 | J12: =Q12+X12 -> 51549 | K12: =R12+Y12 -> 147786 | N12: =INDEX('Subscribers & Revenue'!$G$19:$BN$19, MATCH('Metrics Dashboard'!N$10, 'Subscribers & Revenue'!$G$6:$BN$6, 0)) -> 1081 | O12: =INDEX('Subscribers & Revenue'!$G$19:$BN$19, MATCH('Metrics Dashboard'!O$10, 'Subscribers & Revenue'!$G$6:$BN$6, 0)) -> 3543 | P12: =INDEX('Subscribers & Revenue'!$G$19:$BN$19, MATCH('Metrics Dashboard'!P$10, 'Subscribers & Revenue'!$G$6:$BN$6, 0)) -> 11148 | Q12: =INDEX('Subscribers & Revenue'!$G$19:$BN$19, MATCH('Metrics Dashboard'!Q$10, 'Subscribers & Revenue'!$G$6:$BN$6, 0)) -> 34984 | R12: =INDEX('Subscribers & Revenue'!$G$19:$BN$19, MATCH('Metrics Dashboard'!R$10, 'Subscribers & Revenue'!$G$6:$BN$6, 0)) -> 109806 | U12: =INDEX('Subscribers & Revenue'!$G$29:$BN$29, MATCH('Metrics Dashboard'!U$10, 'Subscribers & Revenue'!$G$6:$BN$6, 0)) -> 982 | V12: =INDEX('Subscribers & Revenue'!$G$29:$BN$29, MATCH('Metrics Dashboard'!V$10, 'Subscribers & Revenue'!$G$6:$BN$6, 0)) -> 2857 | W12: =INDEX('Subscribers & Revenue'!$G$29:$BN$29, MATCH('Metrics Dashboard'!W$10, 'Subscribers & Revenue'!$G$6:$BN$6, 0)) -> 7073 | X12: =INDEX('Subscribers & Revenue'!$G$29:$BN$29, MATCH('Metrics Dashboard'!X$10, 'Subscribers & Revenue'!$G$6:$BN$6, 0)) -> 16565 | Y12: =INDEX('Subscribers & Revenue'!$G$29:$BN$29, MATCH('Metrics Dashboard'!Y$10, 'Subscribers & Revenue'!$G$6:$BN$6, 0)) -> 37980
C13: YoY Growth % | H13: =H12/G12-1 -> 2.1022782 | I13: =I12/H12-1 -> 1.8470313 | J13: =J12/I12-1 -> 1.8290983 | K13: =K12/J12-1 -> 1.8669033 | O13: =O12/N12-1 -> 2.2775208 | P13: =P12/O12-1 -> 2.146486 | Q13: =Q12/P12-1 -> 2.1381414 | R13: =R12/Q12-1 -> 2.1387491 | V13: =V12/U12-1 -> 1.9093686 | W13: =W12/V12-1 -> 1.4756738 | X13: =X12/W12-1 -> 1.3420048 | Y13: =Y12/X12-1 -> 1.292786
C15: ARR | G15: =N15+U15 -> 713220 | H15: =O15+V15 -> 2218290 | I15: =P15+W15 -> 6136830 | J15: =Q15+X15 -> 17374290 | K15: =R15+Y15 -> 50306640 | N15: =N18*12 -> 389160 | O15: =O18*12 -> 1275480 | P15: =P18*12 -> 4013280 | Q15: =Q18*12 -> 12594240 | R15: =R18*12 -> 39530160 | U15: =U18*12 -> 324060 | V15: =V18*12 -> 942810 | W15: =W18*12 -> 2123550 | X15: =X18*12 -> 4780050 | Y15: =Y18*12 -> 10776480
C16: YoY Growth % | H16: =H15/G15-1 -> 2.1102465 | I16: =I15/H15-1 -> 1.7664688 | J16: =J15/I15-1 -> 1.8311506 | K16: =K15/J15-1 -> 1.8954645 | O16: =O15/N15-1 -> 2.2775208 | P16: =P15/O15-1 -> 2.146486 | Q16: =Q15/P15-1 -> 2.1381414 | R16: =R15/Q15-1 -> 2.1387491 | V16: =V15/U15-1 -> 1.9093686 | W16: =W15/V15-1 -> 1.2523626 | X16: =X15/W15-1 -> 1.2509713 | Y16: =Y15/X15-1 -> 1.2544701
C18: MRR | G18: =N18+U18 -> 59435 | H18: =O18+V18 -> 184857.5 | I18: =P18+W18 -> 511402.5 | J18: =Q18+X18 -> 1447857.5 | K18: =R18+Y18 -> 4192220 | N18: =INDEX('Subscribers & Revenue'!$G$68:$BN$68, MATCH('Metrics Dashboard'!N$10, 'Subscribers & Revenue'!$G$6:$BN$6, 0)) -> 32430 | O18: =INDEX('Subscribers & Revenue'!$G$68:$BN$68, MATCH('Metrics Dashboard'!O$10, 'Subscribers & Revenue'!$G$6:$BN$6, 0)) -> 106290 | P18: =INDEX('Subscribers & Revenue'!$G$68:$BN$68, MATCH('Metrics Dashboard'!P$10, 'Subscribers & Revenue'!$G$6:$BN$6, 0)) -> 334440 | Q18: =INDEX('Subscribers & Revenue'!$G$68:$BN$68, MATCH('Metrics Dashboard'!Q$10, 'Subscribers & Revenue'!$G$6:$BN$6, 0)) -> 1049520 | R18: =INDEX('Subscribers & Revenue'!$G$68:$BN$68, MATCH('Metrics Dashboard'!R$10, 'Subscribers & Revenue'!$G$6:$BN$6, 0)) -> 3294180 | U18: =INDEX('Subscribers & Revenue'!$G$69:$BN$69, MATCH('Metrics Dashboard'!U$10, 'Subscribers & Revenue'!$G$6:$BN$6, 0)) -> 27005 | V18: =INDEX('Subscribers & Revenue'!$G$69:$BN$69, MATCH('Metrics Dashboard'!V$10, 'Subscribers & Revenue'!$G$6:$BN$6, 0)) -> 78567.5 | W18: =INDEX('Subscribers & Revenue'!$G$69:$BN$69, MATCH('Metrics Dashboard'!W$10, 'Subscribers & Revenue'!$G$6:$BN$6, 0)) -> 176962.5 | X18: =INDEX('Subscribers & Revenue'!$G$69:$BN$69, MATCH('Metrics Dashboard'!X$10, 'Subscribers & Revenue'!$G$6:$BN$6, 0)) -> 398337.5 | Y18: =INDEX('Subscribers & Revenue'!$G$69:$BN$69, MATCH('Metrics Dashboard'!Y$10, 'Subscribers & Revenue'!$G$6:$BN$6, 0)) -> 898040
C19: YoY Growth % | H19: =H18/G18-1 -> 2.1102465 | I19: =I18/H18-1 -> 1.7664688 | J19: =J18/I18-1 -> 1.8311506 | K19: =K18/J18-1 -> 1.8954645 | O19: =O18/N18-1 -> 2.2775208 | P19: =P18/O18-1 -> 2.146486 | Q19: =Q18/P18-1 -> 2.1381414 | R19: =R18/Q18-1 -> 2.1387491 | V19: =V18/U18-1 -> 1.9093686 | W19: =W18/V18-1 -> 1.2523626 | X19: =X18/W18-1 -> 1.2509713 | Y19: =Y18/X18-1 -> 1.2544701
C21: Deferred Revenue Balance | G21: =-INDEX('Subscribers & Revenue'!$G$77:$BN$77, MATCH('Metrics Dashboard'!G$10, 'Subscribers & Revenue'!$G$6:$BN$6, 0)) -> 170060 | H21: =-INDEX('Subscribers & Revenue'!$G$77:$BN$77, MATCH('Metrics Dashboard'!H$10, 'Subscribers & Revenue'!$G$6:$BN$6, 0)) -> 494587.5 | I21: =-INDEX('Subscribers & Revenue'!$G$77:$BN$77, MATCH('Metrics Dashboard'!I$10, 'Subscribers & Revenue'!$G$6:$BN$6, 0)) -> 1114190 | J21: =-INDEX('Subscribers & Revenue'!$G$77:$BN$77, MATCH('Metrics Dashboard'!J$10, 'Subscribers & Revenue'!$G$6:$BN$6, 0)) -> 2509155 | K21: =-INDEX('Subscribers & Revenue'!$G$77:$BN$77, MATCH('Metrics Dashboard'!K$10, 'Subscribers & Revenue'!$G$6:$BN$6, 0)) -> 5655732.5
C22: YoY Growth % | H22: =H21/G21-1 -> 1.9083118 | I22: =I21/H21-1 -> 1.2527662 | J22: =J21/I21-1 -> 1.2519992 | K22: =K21/J21-1 -> 1.2540387
C24: ARPU (Monthly) | G24: =INDEX('Detailed Metrics'!$G$53:$BN$53, MATCH('Metrics Dashboard'!G$10, 'Detailed Metrics'!$G$6:$BN$6, 0)) -> 28.809985 | H24: =INDEX('Detailed Metrics'!$G$53:$BN$53, MATCH('Metrics Dashboard'!H$10, 'Detailed Metrics'!$G$6:$BN$6, 0)) -> 28.883984 | I24: =INDEX('Detailed Metrics'!$G$53:$BN$53, MATCH('Metrics Dashboard'!I$10, 'Detailed Metrics'!$G$6:$BN$6, 0)) -> 28.066654 | J24: =INDEX('Detailed Metrics'!$G$53:$BN$53, MATCH('Metrics Dashboard'!J$10, 'Detailed Metrics'!$G$6:$BN$6, 0)) -> 28.087014 | K24: =INDEX('Detailed Metrics'!$G$53:$BN$53, MATCH('Metrics Dashboard'!K$10, 'Detailed Metrics'!$G$6:$BN$6, 0)) -> 28.366828 | N24: =INDEX('Detailed Metrics'!$G$51:$BN$51, MATCH('Metrics Dashboard'!N$10, 'Detailed Metrics'!$G$6:$BN$6, 0)) -> 30 | O24: =INDEX('Detailed Metrics'!$G$51:$BN$51, MATCH('Metrics Dashboard'!O$10, 'Detailed Metrics'!$G$6:$BN$6, 0)) -> 30 | P24: =INDEX('Detailed Metrics'!$G$51:$BN$51, MATCH('Metrics Dashboard'!P$10, 'Detailed Metrics'!$G$6:$BN$6, 0)) -> 30 | Q24: =INDEX('Detailed Metrics'!$G$51:$BN$51, MATCH('Metrics Dashboard'!Q$10, 'Detailed Metrics'!$G$6:$BN$6, 0)) -> 30 | R24: =INDEX('Detailed Metrics'!$G$51:$BN$51, MATCH('Metrics Dashboard'!R$10, 'Detailed Metrics'!$G$6:$BN$6, 0)) -> 30 | U24: =INDEX('Detailed Metrics'!$G$52:$BN$52, MATCH('Metrics Dashboard'!U$10, 'Detailed Metrics'!$G$6:$BN$6, 0)) -> 27.5 | V24: =INDEX('Detailed Metrics'!$G$52:$BN$52, MATCH('Metrics Dashboard'!V$10, 'Detailed Metrics'!$G$6:$BN$6, 0)) -> 27.5 | W24: =INDEX('Detailed Metrics'!$G$52:$BN$52, MATCH('Metrics Dashboard'!W$10, 'Detailed Metrics'!$G$6:$BN$6, 0)) -> 25.01944 | X24: =INDEX('Detailed Metrics'!$G$52:$BN$52, MATCH('Metrics Dashboard'!X$10, 'Detailed Metrics'!$G$6:$BN$6, 0)) -> 24.046936 | Y24: =INDEX('Detailed Metrics'!$G$52:$BN$52, MATCH('Metrics Dashboard'!Y$10, 'Detailed Metrics'!$G$6:$BN$6, 0)) -> 23.645076 | AL24: x
C26: Churn Rate | N26: ='Detailed Metrics'!$E$55 -> 0.15 | O26: ='Detailed Metrics'!$E$55 -> 0.15 | P26: ='Detailed Metrics'!$E$55 -> 0.15 | Q26: ='Detailed Metrics'!$E$55 -> 0.15 | R26: ='Detailed Metrics'!$E$55 -> 0.15 | U26: ='Detailed Metrics'!$E$56 -> 0.35 | V26: ='Detailed Metrics'!$E$56 -> 0.35 | W26: ='Detailed Metrics'!$E$56 -> 0.35 | X26: ='Detailed Metrics'!$E$56 -> 0.35 | Y26: ='Detailed Metrics'!$E$56 -> 0.35 | AL26: x
C28: Lifetime (months) | G28: =INDEX('Detailed Metrics'!$G$57:$BN$57, MATCH('Metrics Dashboard'!G$10, 'Detailed Metrics'!$G$6:$BN$6, 0)) -> 19.813494 | H28: =INDEX('Detailed Metrics'!$G$57:$BN$57, MATCH('Metrics Dashboard'!H$10, 'Detailed Metrics'!$G$6:$BN$6, 0)) -> 18.995982 | I28: =INDEX('Detailed Metrics'!$G$57:$BN$57, MATCH('Metrics Dashboard'!I$10, 'Detailed Metrics'!$G$6:$BN$6, 0)) -> 17.387786 | J28: =INDEX('Detailed Metrics'!$G$57:$BN$57, MATCH('Metrics Dashboard'!J$10, 'Detailed Metrics'!$G$6:$BN$6, 0)) -> 15.541902 | K28: =INDEX('Detailed Metrics'!$G$57:$BN$57, MATCH('Metrics Dashboard'!K$10, 'Detailed Metrics'!$G$6:$BN$6, 0)) -> 13.764575 | N28: =INDEX('Detailed Metrics'!$G$55:$BN$55, MATCH('Metrics Dashboard'!N$10, 'Detailed Metrics'!$G$6:$BN$6, 0)) -> 6.6666667 | O28: =INDEX('Detailed Metrics'!$G$55:$BN$55, MATCH('Metrics Dashboard'!O$10, 'Detailed Metrics'!$G$6:$BN$6, 0)) -> 6.6666667 | P28: =INDEX('Detailed Metrics'!$G$55:$BN$55, MATCH('Metrics Dashboard'!P$10, 'Detailed Metrics'!$G$6:$BN$6, 0)) -> 6.6666667 | Q28: =INDEX('Detailed Metrics'!$G$55:$BN$55, MATCH('Metrics Dashboard'!Q$10, 'Detailed Metrics'!$G$6:$BN$6, 0)) -> 6.6666667 | R28: =INDEX('Detailed Metrics'!$G$55:$BN$55, MATCH('Metrics Dashboard'!R$10, 'Detailed Metrics'!$G$6:$BN$6, 0)) -> 6.6666667 | U28: =INDEX('Detailed Metrics'!$G$56:$BN$56, MATCH('Metrics Dashboard'!U$10, 'Detailed Metrics'!$G$6:$BN$6, 0)) -> 34.285714 | V28: =INDEX('Detailed Metrics'!$G$56:$BN$56, MATCH('Metrics Dashboard'!V$10, 'Detailed Metrics'!$G$6:$BN$6, 0)) -> 34.285714 | W28: =INDEX('Detailed Metrics'!$G$56:$BN$56, MATCH('Metrics Dashboard'!W$10, 'Detailed Metrics'!$G$6:$BN$6, 0)) -> 34.285714 | X28: =INDEX('Detailed Metrics'!$G$56:$BN$56, MATCH('Metrics Dashboard'!X$10, 'Detailed Metrics'!$G$6:$BN$6, 0)) -> 34.285714 | Y28: =INDEX('Detailed Metrics'!$G$56:$BN$56, MATCH('Metrics Dashboard'!Y$10, 'Detailed Metrics'!$G$6:$BN$6, 0)) -> 34.285714 | AL28: x
C30: LTV | G30: =INDEX('Detailed Metrics'!$G$61:$BN$61, MATCH('Metrics Dashboard'!G$10, 'Detailed Metrics'!$G$6:$BN$6, 0)) -> 553.60432 | H30: =INDEX('Detailed Metrics'!$G$61:$BN$61, MATCH('Metrics Dashboard'!H$10, 'Detailed Metrics'!$G$6:$BN$6, 0)) -> 531.61607 | I30: =INDEX('Detailed Metrics'!$G$61:$BN$61, MATCH('Metrics Dashboard'!I$10, 'Detailed Metrics'!$G$6:$BN$6, 0)) -> 455.34744 | J30: =INDEX('Detailed Metrics'!$G$61:$BN$61, MATCH('Metrics Dashboard'!J$10, 'Detailed Metrics'!$G$6:$BN$6, 0)) -> 400.66899 | K30: =INDEX('Detailed Metrics'!$G$61:$BN$61, MATCH('Metrics Dashboard'!K$10, 'Detailed Metrics'!$G$6:$BN$6, 0)) -> 356.94276 | N30: =INDEX('Detailed Metrics'!$G$59:$BN$59, MATCH('Metrics Dashboard'!N$10, 'Detailed Metrics'!$G$6:$BN$6, 0)) -> 200 | O30: =INDEX('Detailed Metrics'!$G$59:$BN$59, MATCH('Metrics Dashboard'!O$10, 'Detailed Metrics'!$G$6:$BN$6, 0)) -> 200 | P30: =INDEX('Detailed Metrics'!$G$59:$BN$59, MATCH('Metrics Dashboard'!P$10, 'Detailed Metrics'!$G$6:$BN$6, 0)) -> 200 | Q30: =INDEX('Detailed Metrics'!$G$59:$BN$59, MATCH('Metrics Dashboard'!Q$10, 'Detailed Metrics'!$G$6:$BN$6, 0)) -> 200 | R30: =INDEX('Detailed Metrics'!$G$59:$BN$59, MATCH('Metrics Dashboard'!R$10, 'Detailed Metrics'!$G$6:$BN$6, 0)) -> 200 | U30: =INDEX('Detailed Metrics'!$G$60:$BN$60, MATCH('Metrics Dashboard'!U$10, 'Detailed Metrics'!$G$6:$BN$6, 0)) -> 942.85714 | V30: =INDEX('Detailed Metrics'!$G$60:$BN$60, MATCH('Metrics Dashboard'!V$10, 'Detailed Metrics'!$G$6:$BN$6, 0)) -> 942.85714 | W30: =INDEX('Detailed Metrics'!$G$60:$BN$60, MATCH('Metrics Dashboard'!W$10, 'Detailed Metrics'!$G$6:$BN$6, 0)) -> 857.80938 | X30: =INDEX('Detailed Metrics'!$G$60:$BN$60, MATCH('Metrics Dashboard'!X$10, 'Detailed Metrics'!$G$6:$BN$6, 0)) -> 824.46639 | Y30: =INDEX('Detailed Metrics'!$G$60:$BN$60, MATCH('Metrics Dashboard'!Y$10, 'Detailed Metrics'!$G$6:$BN$6, 0)) -> 810.68833 | AL30: x
C32: Payback (months) | G32: =INDEX('Detailed Metrics'!$G$65:$BN$65, MATCH('Metrics Dashboard'!G$10, 'Detailed Metrics'!$G$6:$BN$6, 0)) -> 4.0208496 | H32: =INDEX('Detailed Metrics'!$G$65:$BN$65, MATCH('Metrics Dashboard'!H$10, 'Detailed Metrics'!$G$6:$BN$6, 0)) -> 3.1941202 | I32: =INDEX('Detailed Metrics'!$G$65:$BN$65, MATCH('Metrics Dashboard'!I$10, 'Detailed Metrics'!$G$6:$BN$6, 0)) -> 2.6043024 | J32: =INDEX('Detailed Metrics'!$G$65:$BN$65, MATCH('Metrics Dashboard'!J$10, 'Detailed Metrics'!$G$6:$BN$6, 0)) -> 2.0577092 | K32: =INDEX('Detailed Metrics'!$G$65:$BN$65, MATCH('Metrics Dashboard'!K$10, 'Detailed Metrics'!$G$6:$BN$6, 0)) -> 1.6101516 | N32: =INDEX('Detailed Metrics'!$G$63:$BN$63, MATCH('Metrics Dashboard'!N$10, 'Detailed Metrics'!$G$6:$BN$6, 0)) -> 2.8579167 | O32: =INDEX('Detailed Metrics'!$G$63:$BN$63, MATCH('Metrics Dashboard'!O$10, 'Detailed Metrics'!$G$6:$BN$6, 0)) -> 2.327791 | P32: =INDEX('Detailed Metrics'!$G$63:$BN$63, MATCH('Metrics Dashboard'!P$10, 'Detailed Metrics'!$G$6:$BN$6, 0)) -> 1.8960003 | Q32: =INDEX('Detailed Metrics'!$G$63:$BN$63, MATCH('Metrics Dashboard'!Q$10, 'Detailed Metrics'!$G$6:$BN$6, 0)) -> 1.5443041 | R32: =INDEX('Detailed Metrics'!$G$63:$BN$63, MATCH('Metrics Dashboard'!R$10, 'Detailed Metrics'!$G$6:$BN$6, 0)) -> 1.2578453 | U32: =INDEX('Detailed Metrics'!$G$64:$BN$64, MATCH('Metrics Dashboard'!U$10, 'Detailed Metrics'!$G$6:$BN$6, 0)) -> 6.6376218 | V32: =INDEX('Detailed Metrics'!$G$64:$BN$64, MATCH('Metrics Dashboard'!V$10, 'Detailed Metrics'!$G$6:$BN$6, 0)) -> 5.8762389 | W32: =INDEX('Detailed Metrics'!$G$64:$BN$64, MATCH('Metrics Dashboard'!W$10, 'Detailed Metrics'!$G$6:$BN$6, 0)) -> 5.7179649 | X32: =INDEX('Detailed Metrics'!$G$64:$BN$64, MATCH('Metrics Dashboard'!X$10, 'Detailed Metrics'!$G$6:$BN$6, 0)) -> 5.2667931 | Y32: =INDEX('Detailed Metrics'!$G$64:$BN$64, MATCH('Metrics Dashboard'!Y$10, 'Detailed Metrics'!$G$6:$BN$6, 0)) -> 4.7418982 | AL32: x
C34: CAC | G34: =INDEX('Detailed Metrics'!$G$43:$BN$43, MATCH('Metrics Dashboard'!G$10, 'Detailed Metrics'!$G$6:$BN$6, 0)) -> 115.84062 | H34: =INDEX('Detailed Metrics'!$G$43:$BN$43, MATCH('Metrics Dashboard'!H$10, 'Detailed Metrics'!$G$6:$BN$6, 0)) -> 92.258918 | I34: =INDEX('Detailed Metrics'!$G$43:$BN$43, MATCH('Metrics Dashboard'!I$10, 'Detailed Metrics'!$G$6:$BN$6, 0)) -> 73.094054 | J34: =INDEX('Detailed Metrics'!$G$43:$BN$43, MATCH('Metrics Dashboard'!J$10, 'Detailed Metrics'!$G$6:$BN$6, 0)) -> 57.794908 | K34: =INDEX('Detailed Metrics'!$G$43:$BN$43, MATCH('Metrics Dashboard'!K$10, 'Detailed Metrics'!$G$6:$BN$6, 0)) -> 45.674892 | N34: =INDEX('Detailed Metrics'!$G$41:$BN$41, MATCH('Metrics Dashboard'!N$10, 'Detailed Metrics'!$G$6:$BN$6, 0)) -> 85.7375 | O34: =INDEX('Detailed Metrics'!$G$41:$BN$41, MATCH('Metrics Dashboard'!O$10, 'Detailed Metrics'!$G$6:$BN$6, 0)) -> 69.83373 | P34: =INDEX('Detailed Metrics'!$G$41:$BN$41, MATCH('Metrics Dashboard'!P$10, 'Detailed Metrics'!$G$6:$BN$6, 0)) -> 56.880009 | Q34: =INDEX('Detailed Metrics'!$G$41:$BN$41, MATCH('Metrics Dashboard'!Q$10, 'Detailed Metrics'!$G$6:$BN$6, 0)) -> 46.329123 | R34: =INDEX('Detailed Metrics'!$G$41:$BN$41, MATCH('Metrics Dashboard'!R$10, 'Detailed Metrics'!$G$6:$BN$6, 0)) -> 37.73536 | U34: =INDEX('Detailed Metrics'!$G$42:$BN$42, MATCH('Metrics Dashboard'!U$10, 'Detailed Metrics'!$G$6:$BN$6, 0)) -> 182.5346 | V34: =INDEX('Detailed Metrics'!$G$42:$BN$42, MATCH('Metrics Dashboard'!V$10, 'Detailed Metrics'!$G$6:$BN$6, 0)) -> 161.59657 | W34: =INDEX('Detailed Metrics'!$G$42:$BN$42, MATCH('Metrics Dashboard'!W$10, 'Detailed Metrics'!$G$6:$BN$6, 0)) -> 143.06028 | X34: =INDEX('Detailed Metrics'!$G$42:$BN$42, MATCH('Metrics Dashboard'!X$10, 'Detailed Metrics'!$G$6:$BN$6, 0)) -> 126.65024 | Y34: =INDEX('Detailed Metrics'!$G$42:$BN$42, MATCH('Metrics Dashboard'!Y$10, 'Detailed Metrics'!$G$6:$BN$6, 0)) -> 112.12254 | AL34: x
C36: LTV/CAC | G36: =G30/G34 -> 4.7790173 | H36: =H30/H34 -> 5.7622188 | I36: =I30/I34 -> 6.2296099 | J36: =J30/J34 -> 6.9326002 | K36: =K30/K34 -> 7.8148572 | N36: =N30/N34 -> 2.3327016 | O36: =O30/O34 -> 2.8639456 | P36: =P30/P34 -> 3.5161738 | Q36: =Q30/Q34 -> 4.316939 | R36: =R30/R34 -> 5.3000687 | U36: =U30/U34 -> 5.1653612 | V36: =V30/V34 -> 5.8346359 | W36: =W30/W34 -> 5.9961393 | X36: =X30/X34 -> 6.5097895 | Y36: =Y30/Y34 -> 7.2303776 | AL36: x
C38: CFO | G38: =INDEX('Detailed Metrics'!$G$89:$BN$89, MATCH('Metrics Dashboard'!G$10, 'Detailed Metrics'!$G$6:$BN$6, 0)) -> -132040.72 | H38: =INDEX('Detailed Metrics'!$G$89:$BN$89, MATCH('Metrics Dashboard'!H$10, 'Detailed Metrics'!$G$6:$BN$6, 0)) -> -240191.72 | I38: =INDEX('Detailed Metrics'!$G$89:$BN$89, MATCH('Metrics Dashboard'!I$10, 'Detailed Metrics'!$G$6:$BN$6, 0)) -> -368801.11 | J38: =INDEX('Detailed Metrics'!$G$89:$BN$89, MATCH('Metrics Dashboard'!J$10, 'Detailed Metrics'!$G$6:$BN$6, 0)) -> -536327.95 | K38: =INDEX('Detailed Metrics'!$G$89:$BN$89, MATCH('Metrics Dashboard'!K$10, 'Detailed Metrics'!$G$6:$BN$6, 0)) -> -838306.96
C40: Burn Multiple | G40: =INDEX('Detailed Metrics'!$G$91:$BN$91, MATCH('Metrics Dashboard'!G$10, 'Detailed Metrics'!$G$6:$BN$6, 0)) -> 20.251644 | H40: =INDEX('Detailed Metrics'!$G$91:$BN$91, MATCH('Metrics Dashboard'!H$10, 'Detailed Metrics'!$G$6:$BN$6, 0)) -> 15.230927 | I40: =INDEX('Detailed Metrics'!$G$91:$BN$91, MATCH('Metrics Dashboard'!I$10, 'Detailed Metrics'!$G$6:$BN$6, 0)) -> 8.7877788 | J40: =INDEX('Detailed Metrics'!$G$91:$BN$91, MATCH('Metrics Dashboard'!J$10, 'Detailed Metrics'!$G$6:$BN$6, 0)) -> 4.4143126 | K40: =INDEX('Detailed Metrics'!$G$91:$BN$91, MATCH('Metrics Dashboard'!K$10, 'Detailed Metrics'!$G$6:$BN$6, 0)) -> 2.3397605

Sheet Detailed Metrics
G4: =YEAR(G6) -> 2024 | H4: =YEAR(H6) -> 2024 | I4: =YEAR(I6) -> 2024 | J4: =YEAR(J6) -> 2024 | K4: =YEAR(K6) -> 2024 | L4: =YEAR(L6) -> 2024 | M4: =YEAR(M6) -> 2024 | N4: =YEAR(N6) -> 2024 | ... BN4: =YEAR(BN6) -> 2028
G5: =ROUNDUP(MONTH(G6)/3,0) -> 1 | H5: =ROUNDUP(MONTH(H6)/3,0) -> 1 | I5: =ROUNDUP(MONTH(I6)/3,0) -> 1 | J5: =ROUNDUP(MONTH(J6)/3,0) -> 2 | K5: =ROUNDUP(MONTH(K6)/3,0) -> 2 | L5: =ROUNDUP(MONTH(L6)/3,0) -> 2 | M5: =ROUNDUP(MONTH(M6)/3,0) -> 3 | N5: =ROUNDUP(MONTH(N6)/3,0) -> 3 | ... BN5: =ROUNDUP(MONTH(BN6)/3,0) -> 4
G6: 45292 | H6: =EDATE($G6,H$7-1) -> 45323 | I6: =EDATE($G6,I$7-1) -> 45352 | J6: =EDATE($G6,J$7-1) -> 45383 | K6: =EDATE($G6,K$7-1) -> 45413 | L6: =EDATE($G6,L$7-1) -> 45444 | M6: =EDATE($G6,M$7-1) -> 45474 | N6: =EDATE($G6,N$7-1) -> 45505 | O6: =EDATE($G6,O$7-1) -> 45536 | ... BN6: =EDATE($G6,BN$7-1) -> 47088
E7: Assumptions | G7: 1 | H7: =G7+1 -> 2 | I7: =H7+1 -> 3 | J7: =I7+1 -> 4 | K7: =J7+1 -> 5 | L7: =K7+1 -> 6 | M7: =L7+1 -> 7 | N7: =M7+1 -> 8 | O7: =N7+1 -> 9 | ... BN7: =BM7+1 -> 60 | BO7: x
A9: x | B9: x | C9: P&L Metrics | BO9: x
BO10: x
C11: Monthly Plan Monthly Revenue | G11: ='Subscribers & Revenue'!G68 -> 2700 | H11: ='Subscribers & Revenue'!H68 -> 5250 | I11: ='Subscribers & Revenue'!I68 -> 7740 | J11: ='Subscribers & Revenue'!J68 -> 10170 | K11: ='Subscribers & Revenue'!K68 -> 12600 | L11: ='Subscribers & Revenue'!L68 -> 15060 | M11: ='Subscribers & Revenue'!M68 -> 17610 | N11: ='Subscribers & Revenue'!N68 -> 20250 | ... BN11: ='Subscribers & Revenue'!BN68 -> 3294180 | BO11: x
C12: % growth | H12: =H11/G11-1 -> 0.94444444 | I12: =I11/H11-1 -> 0.47428571 | J12: =J11/I11-1 -> 0.31395349 | K12: =K11/J11-1 -> 0.23893805 | L12: =L11/K11-1 -> 0.1952381 | M12: =M11/L11-1 -> 0.16932271 | N12: =N11/M11-1 -> 0.14991482 | O12: =O11/N11-1 -> 0.13777778 | ... BN12: =BN11/BM11-1 -> 0.10001803 | BO12: x
BO13: x
C14: Annual Plan Monthly Revenue | G14: ='Subscribers & Revenue'!G69 -> 1512.5 | H14: ='Subscribers & Revenue'!H69 -> 3135 | I14: ='Subscribers & Revenue'!I69 -> 4867.5 | J14: ='Subscribers & Revenue'!J69 -> 6710 | K14: ='Subscribers & Revenue'!K69 -> 8690 | L14: ='Subscribers & Revenue'!L69 -> 10807.5 | M14: ='Subscribers & Revenue'!M69 -> 13062.5 | N14: ='Subscribers & Revenue'!N69 -> 15482.5 | ... BN14: ='Subscribers & Revenue'!BN69 -> 898040 | BO14: x
C15: % growth | H15: =H14/G14-1 -> 1.0727273 | I15: =I14/H14-1 -> 0.55263158 | J15: =J14/I14-1 -> 0.37853107 | K15: =K14/J14-1 -> 0.29508197 | L15: =L14/K14-1 -> 0.24367089 | M15: =M14/L14-1 -> 0.2086514 | N15: =N14/M14-1 -> 0.18526316 | O15: =O14/N14-1 -> 0.1669627 | ... BN15: =BN14/BM14-1 -> 0.070021954 | BO15: x
BO16: x
B17: x | C17: MRR | G17: =SUM(G14,G11) -> 4212.5 | H17: =SUM(H14,H11) -> 8385 | I17: =SUM(I14,I11) -> 12607.5 | J17: =SUM(J14,J11) -> 16880 | K17: =SUM(K14,K11) -> 21290 | L17: =SUM(L14,L11) -> 25867.5 | M17: =SUM(M14,M11) -> 30672.5 | N17: =SUM(N14,N11) -> 35732.5 | ... BN17: =SUM(BN14,BN11) -> 4192220 | BO17: x
C18: % growth | H18: =H17/G17-1 -> 0.99050445 | I18: =I17/H17-1 -> 0.50357782 | J18: =J17/I17-1 -> 0.33888558 | K18: =K17/J17-1 -> 0.26125592 | L18: =L17/K17-1 -> 0.21500705 | M18: =M17/L17-1 -> 0.18575432 | N18: =N17/M17-1 -> 0.16496862 | O18: =O17/N17-1 -> 0.15042328 | ... AD18: =AD17/AC17-1 -> 0.093265321 | BO18: x
BO19: x
C20: Monthly Plan Annual Revenue | G20: =G11*12 -> 32400 | H20: =H11*12 -> 63000 | I20: =I11*12 -> 92880 | J20: =J11*12 -> 122040 | K20: =K11*12 -> 151200 | L20: =L11*12 -> 180720 | M20: =M11*12 -> 211320 | N20: =N11*12 -> 243000 | ... BN20: =BN11*12 -> 39530160 | BO20: x
C21: % growth | H21: =H20/G20-1 -> 0.94444444 | I21: =I20/H20-1 -> 0.47428571 | J21: =J20/I20-1 -> 0.31395349 | K21: =K20/J20-1 -> 0.23893805 | L21: =L20/K20-1 -> 0.1952381 | M21: =M20/L20-1 -> 0.16932271 | N21: =N20/M20-1 -> 0.14991482 | O21: =O20/N20-1 -> 0.13777778 | ... BN21: =BN20/BM20-1 -> 0.10001803 | BO21: x
BO22: x
C23: Annual Plan Annual Revenue | G23: =G14*12 -> 18150 | H23: =H14*12 -> 37620 | I23: =I14*12 -> 58410 | J23: =J14*12 -> 80520 | K23: =K14*12 -> 104280 | L23: =L14*12 -> 129690 | M23: =M14*12 -> 156750 | N23: =N14*12 -> 185790 | ... BN23: =BN14*12 -> 10776480 | BO23: x
C24: % growth | H24: =H23/G23-1 -> 1.0727273 | I24: =I23/H23-1 -> 0.55263158 | J24: =J23/I23-1 -> 0.37853107 | K24: =K23/J23-1 -> 0.29508197 | L24: =L23/K23-1 -> 0.24367089 | M24: =M23/L23-1 -> 0.2086514 | N24: =N23/M23-1 -> 0.18526316 | O24: =O23/N23-1 -> 0.1669627 | ... BN24: =BN23/BM23-1 -> 0.070021954 | BO24: x
BO25: x
B26: x | C26: ARR | G26: =SUM(G23,G20) -> 50550 | H26: =SUM(H23,H20) -> 100620 | I26: =SUM(I23,I20) -> 151290 | J26: =SUM(J23,J20) -> 202560 | K26: =SUM(K23,K20) -> 255480 | L26: =SUM(L23,L20) -> 310410 | M26: =SUM(M23,M20) -> 368070 | N26: =SUM(N23,N20) -> 428790 | ... BN26: =SUM(BN23,BN20) -> 50306640 | BO26: x
C27: % growth | H27: =H26/G26-1 -> 0.99050445 | I27: =I26/H26-1 -> 0.50357782 | J27: =J26/I26-1 -> 0.33888558 | K27: =K26/J26-1 -> 0.26125592 | L27: =L26/K26-1 -> 0.21500705 | M27: =M26/L26-1 -> 0.18575432 | N27: =N26/M26-1 -> 0.16496862 | O27: =O26/N26-1 -> 0.15042328 | ... AD27: =AD26/AC26-1 -> 0.093265321 | BO27: x
BO28: x
A29: x | B29: x | C29: Subscriber Metrics | BO29: x
BO30: x
C31: Active Monthly Subscribers | G31: ='Subscribers & Revenue'!G19 -> 90 | H31: ='Subscribers & Revenue'!H19 -> 175 | I31: ='Subscribers & Revenue'!I19 -> 258 | J31: ='Subscribers & Revenue'!J19 -> 339 | K31: ='Subscribers & Revenue'!K19 -> 420 | L31: ='Subscribers & Revenue'!L19 -> 502 | M31: ='Subscribers & Revenue'!M19 -> 587 | N31: ='Subscribers & Revenue'!N19 -> 675 | ... BN31: ='Subscribers & Revenue'!BN19 -> 109806 | BO31: x
H32: =H31/G31-1 -> 0.94444444 | I32: =I31/H31-1 -> 0.47428571 | J32: =J31/I31-1 -> 0.31395349 | K32: =K31/J31-1 -> 0.23893805 | L32: =L31/K31-1 -> 0.1952381 | M32: =M31/L31-1 -> 0.16932271 | N32: =N31/M31-1 -> 0.14991482 | O32: =O31/N31-1 -> 0.13777778 | ... BN32: =BN31/BM31-1 -> 0.10001803 | BO32: x
C33: Active Annual Subscribers | G33: ='Subscribers & Revenue'!G29 -> 55 | H33: ='Subscribers & Revenue'!H29 -> 114 | I33: ='Subscribers & Revenue'!I29 -> 177 | J33: ='Subscribers & Revenue'!J29 -> 244 | K33: ='Subscribers & Revenue'!K29 -> 316 | L33: ='Subscribers & Revenue'!L29 -> 393 | M33: ='Subscribers & Revenue'!M29 -> 475 | N33: ='Subscribers & Revenue'!N29 -> 563 | ... BN33: ='Subscribers & Revenue'!BN29 -> 37980 | BO33: x
H34: =H33/G33-1 -> 1.0727273 | I34: =I33/H33-1 -> 0.55263158 | J34: =J33/I33-1 -> 0.37853107 | K34: =K33/J33-1 -> 0.29508197 | L34: =L33/K33-1 -> 0.24367089 | M34: =M33/L33-1 -> 0.2086514 | N34: =N33/M33-1 -> 0.18526316 | O34: =O33/N33-1 -> 0.1669627 | ... BN34: =BN33/BM33-1 -> 0.071035786 | BO34: x
B35: x | C35: Active Total Subscribers | G35: =SUM(G31,G33) -> 145 | H35: =SUM(H31,H33) -> 289 | I35: =SUM(I31,I33) -> 435 | J35: =SUM(J31,J33) -> 583 | K35: =SUM(K31,K33) -> 736 | L35: =SUM(L31,L33) -> 895 | M35: =SUM(M31,M33) -> 1062 | N35: =SUM(N31,N33) -> 1238 | ... BN35: =SUM(BN31,BN33) -> 147786 | BO35: x
BO36: x
C37: New Monthly Subscribers | G37: ='Detailed Financials'!G18 -> 90 | H37: ='Detailed Financials'!H18 -> 99 | I37: ='Detailed Financials'!I18 -> 109 | J37: ='Detailed Financials'!J18 -> 120 | K37: ='Detailed Financials'!K18 -> 132 | L37: ='Detailed Financials'!L18 -> 145 | M37: ='Detailed Financials'!M18 -> 160 | N37: ='Detailed Financials'!N18 -> 176 | ... BN37: ='Detailed Financials'!BN18 -> 24957 | BO37: x
C38: New Annual Subscribers | G38: ='Detailed Financials'!G19 -> 55 | H38: ='Detailed Financials'!H19 -> 59 | I38: ='Detailed Financials'!I19 -> 63 | J38: ='Detailed Financials'!J19 -> 67 | K38: ='Detailed Financials'!K19 -> 72 | L38: ='Detailed Financials'!L19 -> 77 | M38: ='Detailed Financials'!M19 -> 82 | N38: ='Detailed Financials'!N19 -> 88 | ... BN38: ='Detailed Financials'!BN19 -> 2982 | BO38: x
C39: Total New Subscribers | G39: =SUM(G37:G38) -> 145 | H39: =SUM(H37:H38) -> 158 | I39: =SUM(I37:I38) -> 172 | J39: =SUM(J37:J38) -> 187 | K39: =SUM(K37:K38) -> 204 | L39: =SUM(L37:L38) -> 222 | M39: =SUM(M37:M38) -> 242 | N39: =SUM(N37:N38) -> 264 | ... BN39: =SUM(BN37:BN38) -> 27939 | BO39: x
BO40: x
C41: Monthly Subscribers CAC | G41: ='Detailed Financials'!G88 -> 100 | H41: ='Detailed Financials'!H88 -> 100 | I41: ='Detailed Financials'!I88 -> 100 | J41: ='Detailed Financials'!J88 -> 95 | K41: ='Detailed Financials'!K88 -> 95 | L41: ='Detailed Financials'!L88 -> 95 | M41: ='Detailed Financials'!M88 -> 90.25 | N41: ='Detailed Financials'!N88 -> 90.25 | ... BN41: ='Detailed Financials'!BN88 -> 37.73536 | BO41: x
C42: Annual Subscribers CAC | G42: ='Detailed Financials'!G92 -> 200 | H42: ='Detailed Financials'!H92 -> 200 | I42: ='Detailed Financials'!I92 -> 200 | J42: ='Detailed Financials'!J92 -> 194 | K42: ='Detailed Financials'!K92 -> 194 | L42: ='Detailed Financials'!L92 -> 194 | M42: ='Detailed Financials'!M92 -> 188.18 | N42: ='Detailed Financials'!N92 -> 188.18 | ... BN42: ='Detailed Financials'!BN92 -> 112.12254 | BO42: x
C43: Blended CAC | G43: =G47/G39 -> 137.93103 | H43: =H47/H39 -> 137.34177 | I43: =I47/I39 -> 136.62791 | J43: =J47/J39 -> 130.47059 | K43: =K47/K39 -> 129.94118 | L43: =L47/L39 -> 129.33784 | M43: =M47/M39 -> 123.43289 | N43: =N47/N39 -> 122.89333 | ... BN43: =BN47/BN39 -> 45.674892 | BO43: x
BO44: x
C45: Monthly Subscribers Total CAC | G45: ='Detailed Financials'!G89 -> 9000 | H45: ='Detailed Financials'!H89 -> 9900 | I45: ='Detailed Financials'!I89 -> 10900 | J45: ='Detailed Financials'!J89 -> 11400 | K45: ='Detailed Financials'!K89 -> 12540 | L45: ='Detailed Financials'!L89 -> 13775 | M45: ='Detailed Financials'!M89 -> 14440 | N45: ='Detailed Financials'!N89 -> 15884 | ... BN45: ='Detailed Financials'!BN89 -> 941761.39 | BO45: x
C46: Annual Subscribers Total CAC | G46: ='Detailed Financials'!G93 -> 11000 | H46: ='Detailed Financials'!H93 -> 11800 | I46: ='Detailed Financials'!I93 -> 12600 | J46: ='Detailed Financials'!J93 -> 12998 | K46: ='Detailed Financials'!K93 -> 13968 | L46: ='Detailed Financials'!L93 -> 14938 | M46: ='Detailed Financials'!M93 -> 15430.76 | N46: ='Detailed Financials'!N93 -> 16559.84 | ... BN46: ='Detailed Financials'!BN93 -> 334349.43 | BO46: x
C47: Total CAC | G47: =SUM(G45:G46) -> 20000 | H47: =SUM(H45:H46) -> 21700 | I47: =SUM(I45:I46) -> 23500 | J47: =SUM(J45:J46) -> 24398 | K47: =SUM(K45:K46) -> 26508 | L47: =SUM(L45:L46) -> 28713 | M47: =SUM(M45:M46) -> 29870.76 | N47: =SUM(N45:N46) -> 32443.84 | ... BN47: =SUM(BN45:BN46) -> 1276110.8 | BO47: x
BO48: x
C49: Monthly LTV Metrics | BO49: x
BO50: x
C51: Monthly Plan ARPU (Monthly) | G51: =G11/G31 -> 30 | H51: =H11/H31 -> 30 | I51: =I11/I31 -> 30 | J51: =J11/J31 -> 30 | K51: =K11/K31 -> 30 | L51: =L11/L31 -> 30 | M51: =M11/M31 -> 30 | N51: =N11/N31 -> 30 | ... BN51: =BN11/BN31 -> 30 | BO51: x
C52: Annual Plan ARPU (Monthly) | G52: =G14/G33 -> 27.5 | H52: =H14/H33 -> 27.5 | I52: =I14/I33 -> 27.5 | J52: =J14/J33 -> 27.5 | K52: =K14/K33 -> 27.5 | L52: =L14/L33 -> 27.5 | M52: =M14/M33 -> 27.5 | N52: =N14/N33 -> 27.5 | ... BN52: =BN14/BN33 -> 23.645076 | BO52: x
C53: Blended ARPU (Monthly) | G53: =G17/G35 -> 29.051724 | H53: =H17/H35 -> 29.013841 | I53: =I17/I35 -> 28.982759 | J53: =J17/J35 -> 28.953688 | K53: =K17/K35 -> 28.92663 | L53: =L17/L35 -> 28.902235 | M53: =M17/M35 -> 28.881827 | N53: =N17/N35 -> 28.863086 | ... BN53: =BN17/BN35 -> 28.366828 | BO53: x
E54: Assumptions | BO54: x
C55: Monthly Plan Subscriber Lifetime (Months) | E55: =1-Assumptions!$E$9 -> 0.15 | G55: =1/$E55 -> 6.6666667 | H55: =1/$E55 -> 6.6666667 | I55: =1/$E55 -> 6.6666667 | J55: =1/$E55 -> 6.6666667 | K55: =1/$E55 -> 6.6666667 | L55: =1/$E55 -> 6.6666667 | M55: =1/$E55 -> 6.6666667 | N55: =1/$E55 -> 6.6666667 | ... BN55: =1/$E55 -> 6.6666667 | BO55: x
C56: Annual Plan Subscriber Lifetime (Months) | E56: =1-Assumptions!$E$16 -> 0.35 | G56: =(1/$E56)*12 -> 34.285714 | H56: =(1/$E56)*12 -> 34.285714 | I56: =(1/$E56)*12 -> 34.285714 | J56: =(1/$E56)*12 -> 34.285714 | K56: =(1/$E56)*12 -> 34.285714 | L56: =(1/$E56)*12 -> 34.285714 | M56: =(1/$E56)*12 -> 34.285714 | N56: =(1/$E56)*12 -> 34.285714 | ... BN56: =(1/$E56)*12 -> 34.285714 | BO56: x
C57: Blended Subscriber Lifetime (Months) | G57: =(G55*G$31+G56*G$33)/G$35 -> 17.142857 | H57: =(H55*H$31+H56*H$33)/H$35 -> 17.561377 | I57: =(I55*I$31+I56*I$33)/I$35 -> 17.904762 | J57: =(J55*J$31+J56*J$33)/J$35 -> 18.225925 | K57: =(K55*K$31+K56*K$33)/K$35 -> 18.524845 | L57: =(L55*L$31+L56*L$33)/L$35 -> 18.79436 | M57: =(M55*M$31+M56*M$33)/M$35 -> 19.019819 | N57: =(N55*N$31+N56*N$33)/N$35 -> 19.226864 | ... BN57: =(BN55*BN$31+BN56*BN$33)/BN$35 -> 13.764575 | BO57: x
BO58: x
C59: Monthly Plan Subscriber LTV | G59: =G55*G51 -> 200 | H59: =H55*H51 -> 200 | I59: =I55*I51 -> 200 | J59: =J55*J51 -> 200 | K59: =K55*K51 -> 200 | L59: =L55*L51 -> 200 | M59: =M55*M51 -> 200 | N59: =N55*N51 -> 200 | ... BN59: =BN55*BN51 -> 200 | BO59: x
C60: Annual Plan Subscriber LTV | G60: =G56*G52 -> 942.85714 | H60: =H56*H52 -> 942.85714 | I60: =I56*I52 -> 942.85714 | J60: =J56*J52 -> 942.85714 | K60: =K56*K52 -> 942.85714 | L60: =L56*L52 -> 942.85714 | M60: =M56*M52 -> 942.85714 | N60: =N56*N52 -> 942.85714 | ... BN60: =BN56*BN52 -> 810.68833 | BO60: x
C61: Blended LTV (Monthly) | G61: =(G59*G$31+G60*G$33)/G$35 -> 481.7734 | H61: =(H59*H$31+H60*H$33)/H$35 -> 493.03015 | I61: =(I59*I$31+I60*I$33)/I$35 -> 502.26601 | J61: =(J59*J$31+J60*J$33)/J$35 -> 510.90419 | K61: =(K59*K$31+K60*K$33)/K$35 -> 518.9441 | L61: =(L59*L$31+L60*L$33)/L$35 -> 526.19314 | M61: =(M59*M$31+M60*M$33)/M$35 -> 532.2572 | N61: =(N59*N$31+N60*N$33)/N$35 -> 537.82599 | ... BN61: =(BN59*BN$31+BN60*BN$33)/BN$35 -> 356.94276 | BO61: x
BO62: x
C63: Monthly Plan Subscriber Payback Period (Months) | G63: =G41/G51 -> 3.3333333 | H63: =H41/H51 -> 3.3333333 | I63: =I41/I51 -> 3.3333333 | J63: =J41/J51 -> 3.1666667 | K63: =K41/K51 -> 3.1666667 | L63: =L41/L51 -> 3.1666667 | M63: =M41/M51 -> 3.0083333 | N63: =N41/N51 -> 3.0083333 | ... BN63: =BN41/BN51 -> 1.2578453 | BO63: x
C64: Annual Plan Subscriber Payback Period (Months) | G64: =G42/G52 -> 7.2727273 | H64: =H42/H52 -> 7.2727273 | I64: =I42/I52 -> 7.2727273 | J64: =J42/J52 -> 7.0545455 | K64: =K42/K52 -> 7.0545455 | L64: =L42/L52 -> 7.0545455 | M64: =M42/M52 -> 6.8429091 | N64: =N42/N52 -> 6.8429091 | ... BN64: =BN42/BN52 -> 4.7418982 | BO64: x
C65: Blended Payback Period | G65: =G43/G53 -> 4.7477745 | H65: =H43/H53 -> 4.7336639 | I65: =I43/I53 -> 4.7141098 | J65: =J43/J53 -> 4.506182 | K65: =K43/K53 -> 4.4920952 | L65: =L43/L53 -> 4.4750117 | M65: =M43/M53 -> 4.2737218 | N65: =N43/N53 -> 4.257803 | ... BN65: =BN43/BN53 -> 1.6101516 | BO65: x
BO66: x
C67: Annual LTV Metrics | BO67: x
BO68: x
C69: Monthly Plan ARPU (Annual) | G69: =G20/G31 -> 360 | H69: =H20/H31 -> 360 | I69: =I20/I31 -> 360 | J69: =J20/J31 -> 360 | K69: =K20/K31 -> 360 | L69: =L20/L31 -> 360 | M69: =M20/M31 -> 360 | N69: =N20/N31 -> 360 | ... BN69: =BN20/BN31 -> 360 | BO69: x
C70: Annual Plan ARPU (Annual) | G70: =G23/G33 -> 330 | H70: =H23/H33 -> 330 | I70: =I23/I33 -> 330 | J70: =J23/J33 -> 330 | K70: =K23/K33 -> 330 | L70: =L23/L33 -> 330 | M70: =M23/M33 -> 330 | N70: =N23/N33 -> 330 | ... BN70: =BN23/BN33 -> 283.74092 | BO70: x
C71: Blended ARPU (Annual) | G71: =G26/G35 -> 348.62069 | H71: =H26/H35 -> 348.16609 | I71: =I26/I35 -> 347.7931 | J71: =J26/J35 -> 347.44425 | K71: =K26/K35 -> 347.11957 | L71: =L26/L35 -> 346.82682 | M71: =M26/M35 -> 346.58192 | N71: =N26/N35 -> 346.35703 | ... BN71: =BN26/BN35 -> 340.40193 | BO71: x
BO72: x
C73: Monthly Plan Subscriber Lifetime (Years) | E73: =1-Assumptions!$E$9 -> 0.15 | G73: =1/$E73/12 -> 0.55555556 | H73: =1/$E73/12 -> 0.55555556 | I73: =1/$E73/12 -> 0.55555556 | J73: =1/$E73/12 -> 0.55555556 | K73: =1/$E73/12 -> 0.55555556 | L73: =1/$E73/12 -> 0.55555556 | M73: =1/$E73/12 -> 0.55555556 | N73: =1/$E73/12 -> 0.55555556 | ... BN73: =1/$E73/12 -> 0.55555556 | BO73: x
C74: Annual Plan Subscriber Lifetime (Years) | E74: =1-Assumptions!$E$16 -> 0.35 | G74: =(1/$E74) -> 2.8571429 | H74: =(1/$E74) -> 2.8571429 | I74: =(1/$E74) -> 2.8571429 | J74: =(1/$E74) -> 2.8571429 | K74: =(1/$E74) -> 2.8571429 | L74: =(1/$E74) -> 2.8571429 | M74: =(1/$E74) -> 2.8571429 | N74: =(1/$E74) -> 2.8571429 | ... BN74: =(1/$E74) -> 2.8571429 | BO74: x
C75: Blended Lifetime (Annual) | G75: =(G73*G$31+G74*G$33)/G$35 -> 1.4285714 | H75: =(H73*H$31+H74*H$33)/H$35 -> 1.4634481 | I75: =(I73*I$31+I74*I$33)/I$35 -> 1.4920635 | J75: =(J73*J$31+J74*J$33)/J$35 -> 1.5188271 | K75: =(K73*K$31+K74*K$33)/K$35 -> 1.5437371 | L75: =(L73*L$31+L74*L$33)/L$35 -> 1.5661967 | M75: =(M73*M$31+M74*M$33)/M$35 -> 1.5849849 | N75: =(N73*N$31+N74*N$33)/N$35 -> 1.6022386 | ... BN75: =(BN73*BN$31+BN74*BN$33)/BN$35 -> 1.1470479 | BO75: x
BO76: x
C77: Monthly Plan Subscriber LTV | G77: =G73*G69 -> 200 | H77: =H73*H69 -> 200 | I77: =I73*I69 -> 200 | J77: =J73*J69 -> 200 | K77: =K73*K69 -> 200 | L77: =L73*L69 -> 200 | M77: =M73*M69 -> 200 | N77: =N73*N69 -> 200 | ... BN77: =BN73*BN69 -> 200 | BO77: x
C78: Annual Plan Subscriber LTV | G78: =G74*G70 -> 942.85714 | H78: =H74*H70 -> 942.85714 | I78: =I74*I70 -> 942.85714 | J78: =J74*J70 -> 942.85714 | K78: =K74*K70 -> 942.85714 | L78: =L74*L70 -> 942.85714 | M78: =M74*M70 -> 942.85714 | N78: =N74*N70 -> 942.85714 | ... BN78: =BN74*BN70 -> 810.68833 | BO78: x
B79: x | C79: Blended LTV (Annual) | G79: =(G77*G$31+G78*G$33)/G$35 -> 481.7734 | H79: =(H77*H$31+H78*H$33)/H$35 -> 493.03015 | I79: =(I77*I$31+I78*I$33)/I$35 -> 502.26601 | J79: =(J77*J$31+J78*J$33)/J$35 -> 510.90419 | K79: =(K77*K$31+K78*K$33)/K$35 -> 518.9441 | L79: =(L77*L$31+L78*L$33)/L$35 -> 526.19314 | M79: =(M77*M$31+M78*M$33)/M$35 -> 532.2572 | N79: =(N77*N$31+N78*N$33)/N$35 -> 537.82599 | ... BN79: =(BN77*BN$31+BN78*BN$33)/BN$35 -> 356.94276 | BO79: x
BO80: x
C81: LTV : CAC | BO81: x
BO82: x
C83: Monthly Plan Subscriber LTV / CAC | G83: =G77/G41 -> 2 | H83: =H77/H41 -> 2 | I83: =I77/I41 -> 2 | J83: =J77/J41 -> 2.1052632 | K83: =K77/K41 -> 2.1052632 | L83: =L77/L41 -> 2.1052632 | M83: =M77/M41 -> 2.2160665 | N83: =N77/N41 -> 2.2160665 | ... BN83: =BN77/BN41 -> 5.3000687 | BO83: x
C84: Annual Plan Subscriber LTV / CAC | G84: =G78/G42 -> 4.7142857 | H84: =H78/H42 -> 4.7142857 | I84: =I78/I42 -> 4.7142857 | J84: =J78/J42 -> 4.8600884 | K84: =K78/K42 -> 4.8600884 | L84: =L78/L42 -> 4.8600884 | M84: =M78/M42 -> 5.0104004 | N84: =N78/N42 -> 5.0104004 | ... BN84: =BN78/BN42 -> 7.2303776 | BO84: x
B85: x | C85: Blended LTV / CAC | G85: =G79/G43 -> 3.4928571 | H85: =H79/H43 -> 3.5898048 | I85: =I79/I43 -> 3.6761597 | J85: =J79/J43 -> 3.9158572 | K85: =K79/K43 -> 3.9936848 | L85: =L79/L43 -> 4.0683619 | M85: =M79/M43 -> 4.312118 | N85: =N79/N43 -> 4.3763642 | ... BN85: =BN79/BN43 -> 7.8148572 | BO85: x
BO86: x
A87: x | B87: x | C87: Cash Metrics | BO87: x
BO88: x
C89: Cash from Operations | G89: ='Detailed Financials'!G188 -> -62375.833 | H89: ='Detailed Financials'!H188 -> -61346.417 | I89: ='Detailed Financials'!I188 -> -60364.6 | J89: ='Detailed Financials'!J188 -> -77566.583 | K89: ='Detailed Financials'!K188 -> -75803.4 | L89: ='Detailed Financials'!L188 -> -74865.217 | M89: ='Detailed Financials'!M188 -> -98609.293 | N89: ='Detailed Financials'!N188 -> -96001.223 | ... BN89: ='Detailed Financials'!BN188 -> -838306.96 | BO89: x
C90: Net New ARR | H90: =H17-G17 -> 4172.5 | I90: =I17-H17 -> 4222.5 | J90: =J17-I17 -> 4272.5 | K90: =K17-J17 -> 4410 | L90: =L17-K17 -> 4577.5 | M90: =M17-L17 -> 4805 | N90: =N17-M17 -> 5060 | O90: =O17-N17 -> 5375 | ... BN90: =BN17-BM17 -> 358287.5 | BO90: x
C91: Burn Multiple | H91: =IF(AND(H89<0, H90>0),ABS(H89)/H90, "NA") -> 14.702556 | I91: =IF(AND(I89<0, I90>0),ABS(I89)/I90, "NA") -> 14.295938 | J91: =IF(AND(J89<0, J90>0),ABS(J89)/J90, "NA") -> 18.154847 | K91: =IF(AND(K89<0, K90>0),ABS(K89)/K90, "NA") -> 17.18898 | L91: =IF(AND(L89<0, L90>0),ABS(L89)/L90, "NA") -> 16.355045 | M91: =IF(AND(M89<0, M90>0),ABS(M89)/M90, "NA") -> 20.522225 | N91: =IF(AND(N89<0, N90>0),ABS(N89)/N90, "NA") -> 18.972574 | O91: =IF(AND(O89<0, O90>0),ABS(O89)/O90, "NA") -> 17.670922 | ... BN91: =IF(AND(BN89<0, BN90>0),ABS(BN89)/BN90, "NA") -> 2.3397605 | BO91: x

Sheet Financials >>>
B3: This sheet was intentionally left blank

Sheet Assumptions
A3: x | B3: x | C3: Model Assumptions
B5: x | C5: Monthly Plan Subscribers
C7: First Month Monthly Subscribers | E7: 90
C8: New Monthly Subscriber Growth | E8: 0.1
C9: Monthly Retention Rate | E9: 0.85
C10: Monthly Plan Price / month | E10: 30
B12: x | C12: Annual Plan Subscribers
C14: First Month Annual Subscribers | E14: 55
C15: New Annual Subscriber Growth | E15: 0.07
C16: Annual Retention Rate | E16: 0.65
C17: Annual Plan Price / year | E17: 330
A19: x | B19: x | C19: Costs
B21: x | C21: COGS
C23: Tech Stack Fees | E23: 0.16
C24: Yearly Savings | E24: -0.005
B26: x | C26: OPEX
C28: Payroll & Headcount
C30: CEO Payroll / year | E30: 150000
C31: CTO Payroll / year | E31: 150000
C32: Engineer Payroll / year | E32: 180000
C33: Support Representative Payroll / year | E33: 60000
C34: Customers per Support Representative | E34: 1000
C35: Executive Payroll / year | E35: 180000
C36: Executive Hiring ARR Milestone | E36: 500000
C37: Yearly Base Salary Increase | E37: 0.08
C38: Additional Costs of Gross Wages | E38: 0.2
C40: G&A % revenue | E40: 0.05
C42: Sales & Marketing
C44: Annual Subscriber CAC | E44: 200
C45: Monthly Subscriber CAC | E45: 100
C46: Monthly Subs CAC Quarterly Improvement | E46: 0.05
C47: Annual Subs CAC Quarterly Improvement | E47: 0.03
C49: Facilities
C51: Rent / month | E51: 10000
C52: First Office Capacity (People) | E52: 20
C53: Utilities / month | E53: 4000
C55: Miscellaneous Expenses (% revenue) | E55: 0.05
B58: x | C58: Taxes
C60: Effective Tax Rate % | E60: 0.21
A62: x | B62: x | C62: Balance Sheet
C64: Founder's Equity | E64: 1000000
C65: DSO | E65: 5
C66: Accounts Payable % ARR | E66: 0.05
C67: OCL % ARR | E67: 0.08
C68: OCL % ARR – Quarterly Decrease | E68: -0.005
C69: End of Period Cash Balance | E69: 1000000

Sheet Summary Financials
G4: =YEAR(G6) -> 2024 | H4: =YEAR(H6) -> 2024 | I4: =YEAR(I6) -> 2024 | J4: =YEAR(J6) -> 2024 | K4: =YEAR(K6) -> 2024 | L4: =YEAR(L6) -> 2024 | M4: =YEAR(M6) -> 2024 | N4: =YEAR(N6) -> 2024 | ... BN4: =YEAR(BN6) -> 2028
G5: =ROUNDUP(MONTH(G6)/3,0) -> 1 | H5: =ROUNDUP(MONTH(H6)/3,0) -> 1 | I5: =ROUNDUP(MONTH(I6)/3,0) -> 1 | J5: =ROUNDUP(MONTH(J6)/3,0) -> 2 | K5: =ROUNDUP(MONTH(K6)/3,0) -> 2 | L5: =ROUNDUP(MONTH(L6)/3,0) -> 2 | M5: =ROUNDUP(MONTH(M6)/3,0) -> 3 | N5: =ROUNDUP(MONTH(N6)/3,0) -> 3 | ... BN5: =ROUNDUP(MONTH(BN6)/3,0) -> 4
G6: 45292 | H6: =EDATE($G6,H$7-1) -> 45323 | I6: =EDATE($G6,I$7-1) -> 45352 | J6: =EDATE($G6,J$7-1) -> 45383 | K6: =EDATE($G6,K$7-1) -> 45413 | L6: =EDATE($G6,L$7-1) -> 45444 | M6: =EDATE($G6,M$7-1) -> 45474 | N6: =EDATE($G6,N$7-1) -> 45505 | O6: =EDATE($G6,O$7-1) -> 45536 | ... BN6: =EDATE($G6,BN$7-1) -> 47088
E7: Assumptions | G7: 1 | H7: =G7+1 -> 2 | I7: =H7+1 -> 3 | J7: =I7+1 -> 4 | K7: =J7+1 -> 5 | L7: =K7+1 -> 6 | M7: =L7+1 -> 7 | N7: =M7+1 -> 8 | O7: =N7+1 -> 9 | ... BN7: =BM7+1 -> 60
A9: x | B9: x | C9: Summary Data
C11: Total Active Subscribers | G11: ='Subscribers & Revenue'!G42 -> 145 | H11: ='Subscribers & Revenue'!H42 -> 289 | I11: ='Subscribers & Revenue'!I42 -> 435 | J11: ='Subscribers & Revenue'!J42 -> 583 | K11: ='Subscribers & Revenue'!K42 -> 736 | L11: ='Subscribers & Revenue'!L42 -> 895 | M11: ='Subscribers & Revenue'!M42 -> 1062 | N11: ='Subscribers & Revenue'!N42 -> 1238 | ... BN11: ='Subscribers & Revenue'!BN42 -> 147786
C12: % growth | H12: =H11/G11-1 -> 0.99310345 | I12: =I11/H11-1 -> 0.50519031 | J12: =J11/I11-1 -> 0.34022989 | K12: =K11/J11-1 -> 0.26243568 | L12: =L11/K11-1 -> 0.21603261 | M12: =M11/L11-1 -> 0.18659218 | N12: =N11/M11-1 -> 0.16572505 | O12: =O11/N11-1 -> 0.15105008 | ... BN12: =BN11/BM11-1 -> 0.092421073
C14: Total New Subscribers | G14: ='Subscribers & Revenue'!G36 -> 145 | H14: ='Subscribers & Revenue'!H36 -> 158 | I14: ='Subscribers & Revenue'!I36 -> 172 | J14: ='Subscribers & Revenue'!J36 -> 187 | K14: ='Subscribers & Revenue'!K36 -> 204 | L14: ='Subscribers & Revenue'!L36 -> 222 | M14: ='Subscribers & Revenue'!M36 -> 242 | N14: ='Subscribers & Revenue'!N36 -> 264 | ... BN14: ='Subscribers & Revenue'!BN36 -> 27939
C15: % growth | H15: =H14/G14-1 -> 0.089655172 | I15: =I14/H14-1 -> 0.088607595 | J15: =J14/I14-1 -> 0.087209302 | K15: =K14/J14-1 -> 0.090909091 | L15: =L14/K14-1 -> 0.088235294 | M15: =M14/L14-1 -> 0.09009009 | N15: =N14/M14-1 -> 0.090909091 | O15: =O14/N14-1 -> 0.090909091 | ... BN15: =BN14/BM14-1 -> 0.096722277
C17: ARR | G17: ='Subscribers & Revenue'!G72 -> 50550 | H17: ='Subscribers & Revenue'!H72 -> 100620 | I17: ='Subscribers & Revenue'!I72 -> 151290 | J17: ='Subscribers & Revenue'!J72 -> 202560 | K17: ='Subscribers & Revenue'!K72 -> 255480 | L17: ='Subscribers & Revenue'!L72 -> 310410 | M17: ='Subscribers & Revenue'!M72 -> 368070 | N17: ='Subscribers & Revenue'!N72 -> 428790 | ... BN17: ='Subscribers & Revenue'!BN72 -> 50306640
C18: % growth | H18: =H17/G17-1 -> 0.99050445 | I18: =I17/H17-1 -> 0.50357782 | J18: =J17/I17-1 -> 0.33888558 | K18: =K17/J17-1 -> 0.26125592 | L18: =L17/K17-1 -> 0.21500705 | M18: =M17/L17-1 -> 0.18575432 | N18: =N17/M17-1 -> 0.16496862 | O18: =O17/N17-1 -> 0.15042328 | ... BN18: =BN17/BM17-1 -> 0.093451697
C20: Bookings | G20: ='Subscribers & Revenue'!G64 -> 20850 | H20: ='Subscribers & Revenue'!H64 -> 24720 | I20: ='Subscribers & Revenue'!I64 -> 28530 | J20: ='Subscribers & Revenue'!J64 -> 32280 | K20: ='Subscribers & Revenue'!K64 -> 36360 | L20: ='Subscribers & Revenue'!L64 -> 40470 | M20: ='Subscribers & Revenue'!M64 -> 44670 | N20: ='Subscribers & Revenue'!N64 -> 49290 | ... BN20: ='Subscribers & Revenue'!BN64 -> 4562370
C21: % growth | H21: =H20/G20-1 -> 0.18561151 | I21: =I20/H20-1 -> 0.15412621 | J21: =J20/I20-1 -> 0.13144059 | K21: =K20/J20-1 -> 0.12639405 | L21: =L20/K20-1 -> 0.1130363 | M21: =M20/L20-1 -> 0.10378058 | N21: =N20/M20-1 -> 0.10342512 | O21: =O20/N20-1 -> 0.096774194 | ... BN21: =BN20/BM20-1 -> 0.091557029
C23: Deferred Revenue (MRR) | G23: ='Subscribers & Revenue'!G76 -> -16637.5 | H23: ='Subscribers & Revenue'!H76 -> -16335 | I23: ='Subscribers & Revenue'!I76 -> -15922.5 | J23: ='Subscribers & Revenue'!J76 -> -15400 | K23: ='Subscribers & Revenue'!K76 -> -15070 | L23: ='Subscribers & Revenue'!L76 -> -14602.5 | M23: ='Subscribers & Revenue'!M76 -> -13997.5 | N23: ='Subscribers & Revenue'!N76 -> -13557.5 | ... BN23: ='Subscribers & Revenue'!BN76 -> -370150
A25: x | B25: x | C25: Income Statement
B27: x | C27: Revenue
C29: Revenue (MRR) | G29: ='Subscribers & Revenue'!G70 -> 4212.5 | H29: ='Subscribers & Revenue'!H70 -> 8385 | I29: ='Subscribers & Revenue'!I70 -> 12607.5 | J29: ='Subscribers & Revenue'!J70 -> 16880 | K29: ='Subscribers & Revenue'!K70 -> 21290 | L29: ='Subscribers & Revenue'!L70 -> 25867.5 | M29: ='Subscribers & Revenue'!M70 -> 30672.5 | N29: ='Subscribers & Revenue'!N70 -> 35732.5 | ... BN29: ='Subscribers & Revenue'!BN70 -> 4192220
C30: % growth | H30: =H29/G29-1 -> 0.99050445 | I30: =I29/H29-1 -> 0.50357782 | J30: =J29/I29-1 -> 0.33888558 | K30: =K29/J29-1 -> 0.26125592 | L30: =L29/K29-1 -> 0.21500705 | M30: =M29/L29-1 -> 0.18575432 | N30: =N29/M29-1 -> 0.16496862 | O30: =O29/N29-1 -> 0.15042328 | ... BN30: =BN29/BM29-1 -> 0.093451697
C32: COGS | G32: ='Detailed Financials'!G43 -> -674 | H32: ='Detailed Financials'!H43 -> -1341.6 | I32: ='Detailed Financials'!I43 -> -2017.2 | J32: ='Detailed Financials'!J43 -> -2700.8 | K32: ='Detailed Financials'!K43 -> -3406.4 | L32: ='Detailed Financials'!L43 -> -4138.8 | M32: ='Detailed Financials'!M43 -> -4907.6 | N32: ='Detailed Financials'!N43 -> -5717.2 | ... BN32: ='Detailed Financials'!BN43 -> -586910.8
C34: Gross Profit | G34: =G32+G29 -> 3538.5 | H34: =H32+H29 -> 7043.4 | I34: =I32+I29 -> 10590.3 | J34: =J32+J29 -> 14179.2 | K34: =K32+K29 -> 17883.6 | L34: =L32+L29 -> 21728.7 | M34: =M32+M29 -> 25764.9 | N34: =N32+N29 -> 30015.3 | ... BN34: =BN32+BN29 -> 3605309.2
C35: % margin | G35: =G34/G$29 -> 0.84 | H35: =H34/H$29 -> 0.84 | I35: =I34/I$29 -> 0.84 | J35: =J34/J$29 -> 0.84 | K35: =K34/K$29 -> 0.84 | L35: =L34/L$29 -> 0.84 | M35: =M34/M$29 -> 0.84 | N35: =N34/N$29 -> 0.84 | ... BN35: =BN34/BN$29 -> 0.86
C37: Payroll | G37: ='Detailed Financials'!G109 -> -54000 | H37: ='Detailed Financials'!H109 -> -54000 | I37: ='Detailed Financials'!I109 -> -54000 | J37: ='Detailed Financials'!J109 -> -72000 | K37: ='Detailed Financials'!K109 -> -72000 | L37: ='Detailed Financials'!L109 -> -72000 | M37: ='Detailed Financials'!M109 -> -96000 | N37: ='Detailed Financials'!N109 -> -96000 | ... BN37: ='Detailed Financials'!BN109 -> -3181199.5
C38: G&A | G38: ='Detailed Financials'!G110 -> -210.625 | H38: ='Detailed Financials'!H110 -> -419.25 | I38: ='Detailed Financials'!I110 -> -630.375 | J38: ='Detailed Financials'!J110 -> -844 | K38: ='Detailed Financials'!K110 -> -1064.5 | L38: ='Detailed Financials'!L110 -> -1293.375 | M38: ='Detailed Financials'!M110 -> -1533.625 | N38: ='Detailed Financials'!N110 -> -1786.625 | ... BN38: ='Detailed Financials'!BN110 -> -209611
C39: S&M | G39: ='Detailed Financials'!G111 -> -20000 | H39: ='Detailed Financials'!H111 -> -21700 | I39: ='Detailed Financials'!I111 -> -23500 | J39: ='Detailed Financials'!J111 -> -24398 | K39: ='Detailed Financials'!K111 -> -26508 | L39: ='Detailed Financials'!L111 -> -28713 | M39: ='Detailed Financials'!M111 -> -29870.76 | N39: ='Detailed Financials'!N111 -> -32443.84 | ... BN39: ='Detailed Financials'!BN111 -> -1276110.8
C40: Facilities | G40: ='Detailed Financials'!G112 -> -14000 | H40: ='Detailed Financials'!H112 -> -14000 | I40: ='Detailed Financials'!I112 -> -14000 | J40: ='Detailed Financials'!J112 -> -14000 | K40: ='Detailed Financials'!K112 -> -14000 | L40: ='Detailed Financials'!L112 -> -14000 | M40: ='Detailed Financials'!M112 -> -14000 | N40: ='Detailed Financials'!N112 -> -14000 | ... BN40: ='Detailed Financials'!BN112 -> -28000
C41: Miscellaneous | G41: ='Detailed Financials'!G113 -> -210.625 | H41: ='Detailed Financials'!H113 -> -419.25 | I41: ='Detailed Financials'!I113 -> -630.375 | J41: ='Detailed Financials'!J113 -> -844 | K41: ='Detailed Financials'!K113 -> -1064.5 | L41: ='Detailed Financials'!L113 -> -1293.375 | M41: ='Detailed Financials'!M113 -> -1533.625 | N41: ='Detailed Financials'!N113 -> -1786.625 | ... BN41: ='Detailed Financials'!BN113 -> -209611
C42: OPEX | G42: =SUM(G37:G41) -> -88421.25 | H42: =SUM(H37:H41) -> -90538.5 | I42: =SUM(I37:I41) -> -92760.75 | J42: =SUM(J37:J41) -> -112086 | K42: =SUM(K37:K41) -> -114637 | L42: =SUM(L37:L41) -> -117299.75 | M42: =SUM(M37:M41) -> -142938.01 | N42: =SUM(N37:N41) -> -146017.09 | ... BN42: =SUM(BN37:BN41) -> -4904532.3
C44: Operating Profit | G44: =G34+G42 -> -84882.75 | H44: =H34+H42 -> -83495.1 | I44: =I34+I42 -> -82170.45 | J44: =J34+J42 -> -97906.8 | K44: =K34+K42 -> -96753.4 | L44: =L34+L42 -> -95571.05 | M44: =M34+M42 -> -117173.11 | N44: =N34+N42 -> -116001.79 | ... BN44: =BN34+BN42 -> -1299223.1
C45: % margin | G45: =G44/G$29 -> -20.150208 | H45: =H44/H$29 -> -9.9576744 | I45: =I44/I$29 -> -6.5175848 | J45: =J44/J$29 -> -5.8001659 | K45: =K44/K$29 -> -4.5445467 | L45: =L44/L$29 -> -3.6946381 | M45: =M44/M$29 -> -3.8201356 | N45: =N44/N$29 -> -3.2463945 | ... BN45: =BN44/BN$29 -> -0.30991292
C47: Taxable Income | G47: ='Detailed Financials'!G127 -> 0 | H47: ='Detailed Financials'!H127 -> 0 | I47: ='Detailed Financials'!I127 -> 0 | J47: ='Detailed Financials'!J127 -> 0 | K47: ='Detailed Financials'!K127 -> 0 | L47: ='Detailed Financials'!L127 -> 0 | M47: ='Detailed Financials'!M127 -> 0 | N47: ='Detailed Financials'!N127 -> 0 | ... BN47: ='Detailed Financials'!BN127 -> 0
C48: Taxes (%) | E48: =Assumptions!E60 -> 0.21 | G48: =$E48 -> 0.21 | H48: =$E48 -> 0.21 | I48: =$E48 -> 0.21 | J48: =$E48 -> 0.21 | K48: =$E48 -> 0.21 | L48: =$E48 -> 0.21 | M48: =$E48 -> 0.21 | N48: =$E48 -> 0.21 | ... BN48: =$E48 -> 0.21
C49: Tax Expense | G49: =-G47*G48 -> 0 | H49: =-H47*H48 -> 0 | I49: =-I47*I48 -> 0 | J49: =-J47*J48 -> 0 | K49: =-K47*K48 -> 0 | L49: =-L47*L48 -> 0 | M49: =-M47*M48 -> 0 | N49: =-N47*N48 -> 0 | ... BN49: =-BN47*BN48 -> 0
B51: x | C51: Net Income | G51: =G44+G49 -> -84882.75 | H51: =H44+H49 -> -83495.1 | I51: =I44+I49 -> -82170.45 | J51: =J44+J49 -> -97906.8 | K51: =K44+K49 -> -96753.4 | L51: =L44+L49 -> -95571.05 | M51: =M44+M49 -> -117173.11 | N51: =N44+N49 -> -116001.79 | ... BN51: =BN44+BN49 -> -1299223.1
A53: x | B53: x | C53: Balance Sheet
B55: x | C55: Assets
C57: Cash & Cash Equivalents | G57: ='Detailed Financials'!G137 -> 937624.17 | H57: ='Detailed Financials'!H137 -> 876277.75 | I57: ='Detailed Financials'!I137 -> 815913.15 | J57: ='Detailed Financials'!J137 -> 738346.57 | K57: ='Detailed Financials'!K137 -> 662543.17 | L57: ='Detailed Financials'!L137 -> 587677.95 | M57: ='Detailed Financials'!M137 -> 489068.66 | N57: ='Detailed Financials'!N137 -> 393067.43 | ... BN57: ='Detailed Financials'!BN137 -> 1000000
C58: Accounts Receivable | G58: ='Detailed Financials'!G141 -> 702.08333 | H58: ='Detailed Financials'!H141 -> 1397.5 | I58: ='Detailed Financials'!I141 -> 2101.25 | J58: ='Detailed Financials'!J141 -> 2813.3333 | K58: ='Detailed Financials'!K141 -> 3548.3333 | L58: ='Detailed Financials'!L141 -> 4311.25 | M58: ='Detailed Financials'!M141 -> 5112.0833 | N58: ='Detailed Financials'!N141 -> 5955.4167 | ... BN58: ='Detailed Financials'!BN141 -> 698703.33
C59: Total Assets | G59: =SUM(G57, G58) -> 938326.25 | H59: =SUM(H57, H58) -> 877675.25 | I59: =SUM(I57, I58) -> 818014.4 | J59: =SUM(J57, J58) -> 741159.9 | K59: =SUM(K57, K58) -> 666091.5 | L59: =SUM(L57, L58) -> 591989.2 | M59: =SUM(M57, M58) -> 494180.74 | N59: =SUM(N57, N58) -> 399022.85 | ... BN59: =SUM(BN57, BN58) -> 1698703.3
B61: x | C61: Liabilities
C63: Accounts Payable | G63: ='Detailed Financials'!G149 -> 2527.5 | H63: ='Detailed Financials'!H149 -> 5031 | I63: ='Detailed Financials'!I149 -> 7564.5 | J63: ='Detailed Financials'!J149 -> 10128 | K63: ='Detailed Financials'!K149 -> 12774 | L63: ='Detailed Financials'!L149 -> 15520.5 | M63: ='Detailed Financials'!M149 -> 18403.5 | N63: ='Detailed Financials'!N149 -> 21439.5 | ... BN63: ='Detailed Financials'!BN149 -> 2515332
C64: Other Current Liabilities | G64: ='Detailed Financials'!G153 -> 4044 | H64: ='Detailed Financials'!H153 -> 8049.6 | I64: ='Detailed Financials'!I153 -> 12103.2 | J64: ='Detailed Financials'!J153 -> 15192 | K64: ='Detailed Financials'!K153 -> 19161 | L64: ='Detailed Financials'!L153 -> 23280.75 | M64: ='Detailed Financials'!M153 -> 25764.9 | N64: ='Detailed Financials'!N153 -> 30015.3 | ... BN64: ='Detailed Financials'!BN153 -> -754599.6
C65: Deferred Revenue | G65: =-G23 -> 16637.5 | H65: =G65-H23 -> 32972.5 | I65: =H65-I23 -> 48895 | J65: =I65-J23 -> 64295 | K65: =J65-K23 -> 79365 | L65: =K65-L23 -> 93967.5 | M65: =L65-M23 -> 107965 | N65: =M65-N23 -> 121522.5 | O65: =N65-O23 -> 134475 | ... BN65: =BM65-BN23 -> 5655732.5
C66: Total Liabilities | G66: =SUM(G64,G63,G65) -> 23209 | H66: =SUM(H64,H63,H65) -> 46053.1 | I66: =SUM(I64,I63,I65) -> 68562.7 | J66: =SUM(J64,J63,J65) -> 89615 | K66: =SUM(K64,K63,K65) -> 111300 | L66: =SUM(L64,L63,L65) -> 132768.75 | M66: =SUM(M64,M63,M65) -> 152133.4 | N66: =SUM(N64,N63,N65) -> 172977.3 | ... BN66: =SUM(BN64,BN63,BN65) -> 7416464.9
B68: x | C68: Equity
C70: Equity | G70: =G103 -> 1000000 | H70: =G70+H103 -> 1000000 | I70: =H70+I103 -> 1000000 | J70: =I70+J103 -> 1000000 | K70: =J70+K103 -> 1000000 | L70: =K70+L103 -> 1000000 | M70: =L70+M103 -> 1000000 | N70: =M70+N103 -> 1000000 | O70: =N70+O103 -> 1000000 | ... BN70: =BM70+BN103 -> 22399064
C71: Retained Earnings | G71: =G51 -> -84882.75 | H71: =G71+H51 -> -168377.85 | I71: =H71+I51 -> -250548.3 | J71: =I71+J51 -> -348455.1 | K71: =J71+K51 -> -445208.5 | L71: =K71+L51 -> -540779.55 | M71: =L71+M51 -> -657952.66 | N71: =M71+N51 -> -773954.45 | O71: =N71+O51 -> -888732.32 | ... BN71: =BM71+BN51 -> -28116825
C73: Total Equity | G73: =SUM(G70,G71) -> 915117.25 | H73: =SUM(H70,H71) -> 831622.15 | I73: =SUM(I70,I71) -> 749451.7 | J73: =SUM(J70,J71) -> 651544.9 | K73: =SUM(K70,K71) -> 554791.5 | L73: =SUM(L70,L71) -> 459220.45 | M73: =SUM(M70,M71) -> 342047.34 | N73: =SUM(N70,N71) -> 226045.55 | ... BN73: =SUM(BN70,BN71) -> -5717761.6
C75: Balance Sheet Check | E75: {=AND(ABS(G75:AD75) < 0.000001)} -> TRUE | G75: =G59-G66-G73 -> 0 | H75: =H59-H66-H73 -> 0 | I75: =I59-I66-I73 -> 0 | J75: =J59-J66-J73 -> 0 | K75: =K59-K66-K73 -> 0 | L75: =L59-L66-L73 -> 0 | M75: =M59-M66-M73 -> 0 | N75: =N59-N66-N73 -> 0 | ... BN75: =BN59-BN66-BN73 -> -7.4505806e-09
A77: x | B77: x | C77: Cash Flow Statement
B79: x | C79: Cash from Operations
C81: Net Income | G81: =G51 -> -84882.75 | H81: =H51 -> -83495.1 | I81: =I51 -> -82170.45 | J81: =J51 -> -97906.8 | K81: =K51 -> -96753.4 | L81: =L51 -> -95571.05 | M81: =M51 -> -117173.11 | N81: =N51 -> -116001.79 | ... BN81: =BN51 -> -1299223.1
C82: (Increase) / Decrease in AR | G82: =F58-G58 -> -702.08333 | H82: =G58-H58 -> -695.41667 | I82: =H58-I58 -> -703.75 | J82: =I58-J58 -> -712.08333 | K82: =J58-K58 -> -735 | L82: =K58-L58 -> -762.91667 | M82: =L58-M58 -> -800.83333 | N82: =M58-N58 -> -843.33333 | ... BN82: =BM58-BN58 -> -59714.583
C83: Increase / (Decrease) in AP | G83: =G63-F63 -> 2527.5 | H83: =H63-G63 -> 2503.5 | I83: =I63-H63 -> 2533.5 | J83: =J63-I63 -> 2563.5 | K83: =K63-J63 -> 2646 | L83: =L63-K63 -> 2746.5 | M83: =M63-L63 -> 2883 | N83: =N63-M63 -> 3036 | ... BN83: =BN63-BM63 -> 214972.5
C84: Increase / (Decrease) in OCL | G84: =G64-F64 -> 4044 | H84: =H64-G64 -> 4005.6 | I84: =I64-H64 -> 4053.6 | J84: =J64-I64 -> 3088.8 | K84: =K64-J64 -> 3969 | L84: =L64-K64 -> 4119.75 | M84: =M64-L64 -> 2484.15 | N84: =N64-M64 -> 4250.4 | ... BN84: =BN64-BM64 -> -64491.75
C85: Increase / (Decrease) in Deferred Revenue | G85: =G65-F65 -> 16637.5 | H85: =H65-G65 -> 16335 | I85: =I65-H65 -> 15922.5 | J85: =J65-I65 -> 15400 | K85: =K65-J65 -> 15070 | L85: =L65-K65 -> 14602.5 | M85: =M65-L65 -> 13997.5 | N85: =N65-M65 -> 13557.5 | ... BN85: =BN65-BM65 -> 370150
C86: Cash from Operations | G86: =SUM(G81:G85) -> -62375.833 | H86: =SUM(H81:H85) -> -61346.417 | I86: =SUM(I81:I85) -> -60364.6 | J86: =SUM(J81:J85) -> -77566.583 | K86: =SUM(K81:K85) -> -75803.4 | L86: =SUM(L81:L85) -> -74865.217 | M86: =SUM(M81:M85) -> -98609.293 | N86: =SUM(N81:N85) -> -96001.223 | ... BN86: =SUM(BN81:BN85) -> -838306.96
B88: x | C88: Cash from Investing
C90: Cash from Investing | G90: =SUM(G89) -> 0 | H90: =SUM(H89) -> 0 | I90: =SUM(I89) -> 0 | J90: =SUM(J89) -> 0 | K90: =SUM(K89) -> 0 | L90: =SUM(L89) -> 0 | M90: =SUM(M89) -> 0 | N90: =SUM(N89) -> 0 | ... BN90: =SUM(BN89) -> 0
B92: x | C92: Cash from Financing
C94: Cash Balance December 2025 | E94: =Assumptions!$E$69 -> 1000000 | G94: ='Detailed Financials'!G192 -> -20399064
C95: Funds to Raise | G95: =IF(G94>E94,0,E94-G94) -> 21399064
B97: x | C97: Fundraise
C99: Runway Month | G99: ='Detailed Financials'!G197 -> 11
C100: Runway Date | G100: ='Detailed Financials'!G198 -> 45597
C101: Memo: Fundraising Start | G101: =G99-6 -> 5
C103: Equity Financing | G103: =Assumptions!$E$64 -> 1000000 | H103: {=_xlfn.IFS($G$99<=1,$G$95, H$7=$G$99,$G$95,1,0)} -> 0 | I103: {=_xlfn.IFS($G$99<=1,$G$95, I$7=$G$99,$G$95,1,0)} -> 0 | J103: {=_xlfn.IFS($G$99<=1,$G$95, J$7=$G$99,$G$95,1,0)} -> 0 | K103: {=_xlfn.IFS($G$99<=1,$G$95, K$7=$G$99,$G$95,1,0)} -> 0 | L103: {=_xlfn.IFS($G$99<=1,$G$95, L$7=$G$99,$G$95,1,0)} -> 0 | M103: {=_xlfn.IFS($G$99<=1,$G$95, M$7=$G$99,$G$95,1,0)} -> 0 | N103: {=_xlfn.IFS($G$99<=1,$G$95, N$7=$G$99,$G$95,1,0)} -> 0 | O103: {=_xlfn.IFS($G$99<=1,$G$95, O$7=$G$99,$G$95,1,0)} -> 0 | ... BN103: {=_xlfn.IFS($G$99<=1,$G$95, BN$7=$G$99,$G$95,1,0)} -> 0
C104: Cash from Financing | G104: =SUM(G103:G103) -> 1000000 | H104: =SUM(H103:H103) -> 0 | I104: =SUM(I103:I103) -> 0 | J104: =SUM(J103:J103) -> 0 | K104: =SUM(K103:K103) -> 0 | L104: =SUM(L103:L103) -> 0 | M104: =SUM(M103:M103) -> 0 | N104: =SUM(N103:N103) -> 0 | ... BN104: =SUM(BN103:BN103) -> 0
B106: x | C106: Net Cash Flow
C108: =C86 -> Cash from Operations | G108: =G86 -> -62375.833 | H108: =H86 -> -61346.417 | I108: =I86 -> -60364.6 | J108: =J86 -> -77566.583 | K108: =K86 -> -75803.4 | L108: =L86 -> -74865.217 | M108: =M86 -> -98609.293 | N108: =N86 -> -96001.223 | ... BN108: =BN86 -> -838306.96
C109: =C90 -> Cash from Investing | G109: =G90 -> 0 | H109: =H90 -> 0 | I109: =I90 -> 0 | J109: =J90 -> 0 | K109: =K90 -> 0 | L109: =L90 -> 0 | M109: =M90 -> 0 | N109: =N90 -> 0 | ... BN109: =BN90 -> 0
C110: =C104 -> Cash from Financing | G110: =G104 -> 1000000 | H110: =H104 -> 0 | I110: =I104 -> 0 | J110: =J104 -> 0 | K110: =K104 -> 0 | L110: =L104 -> 0 | M110: =M104 -> 0 | N110: =N104 -> 0 | ... BN110: =BN104 -> 0
C111: Net Cash Flow | G111: =SUM(G108:G110) -> 937624.17 | H111: =SUM(H108:H110) -> -61346.417 | I111: =SUM(I108:I110) -> -60364.6 | J111: =SUM(J108:J110) -> -77566.583 | K111: =SUM(K108:K110) -> -75803.4 | L111: =SUM(L108:L110) -> -74865.217 | M111: =SUM(M108:M110) -> -98609.293 | N111: =SUM(N108:N110) -> -96001.223 | ... BN111: =SUM(BN108:BN110) -> -838306.96
C113: Beginning Cash | G113: =F115 -> 0 | H113: =G115 -> 937624.17 | I113: =H115 -> 876277.75 | J113: =I115 -> 815913.15 | K113: =J115 -> 738346.57 | L113: =K115 -> 662543.17 | M113: =L115 -> 587677.95 | N113: =M115 -> 489068.66 | ... BN113: =BM115 -> 1838307
C114: Net Cash Flow | G114: =G111 -> 937624.17 | H114: =H111 -> -61346.417 | I114: =I111 -> -60364.6 | J114: =J111 -> -77566.583 | K114: =K111 -> -75803.4 | L114: =L111 -> -74865.217 | M114: =M111 -> -98609.293 | N114: =N111 -> -96001.223 | ... BN114: =BN111 -> -838306.96
C115: Ending Cash | G115: =SUM(G113:G114) -> 937624.17 | H115: =SUM(H113:H114) -> 876277.75 | I115: =SUM(I113:I114) -> 815913.15 | J115: =SUM(J113:J114) -> 738346.57 | K115: =SUM(K113:K114) -> 662543.17 | L115: =SUM(L113:L114) -> 587677.95 | M115: =SUM(M113:M114) -> 489068.66 | N115: =SUM(N113:N114) -> 393067.43 | ... BN115: =SUM(BN113:BN114) -> 1000000

Sheet Detailed Financials
G4: =YEAR(G6) -> 2024 | H4: =YEAR(H6) -> 2024 | I4: =YEAR(I6) -> 2024 | J4: =YEAR(J6) -> 2024 | K4: =YEAR(K6) -> 2024 | L4: =YEAR(L6) -> 2024 | M4: =YEAR(M6) -> 2024 | N4: =YEAR(N6) -> 2024 | ... BN4: =YEAR(BN6) -> 2028
G5: =ROUNDUP(MONTH(G6)/3,0) -> 1 | H5: =ROUNDUP(MONTH(H6)/3,0) -> 1 | I5: =ROUNDUP(MONTH(I6)/3,0) -> 1 | J5: =ROUNDUP(MONTH(J6)/3,0) -> 2 | K5: =ROUNDUP(MONTH(K6)/3,0) -> 2 | L5: =ROUNDUP(MONTH(L6)/3,0) -> 2 | M5: =ROUNDUP(MONTH(M6)/3,0) -> 3 | N5: =ROUNDUP(MONTH(N6)/3,0) -> 3 | ... BN5: =ROUNDUP(MONTH(BN6)/3,0) -> 4
G6: 45292 | H6: =EDATE($G6,H$7-1) -> 45323 | I6: =EDATE($G6,I$7-1) -> 45352 | J6: =EDATE($G6,J$7-1) -> 45383 | K6: =EDATE($G6,K$7-1) -> 45413 | L6: =EDATE($G6,L$7-1) -> 45444 | M6: =EDATE($G6,M$7-1) -> 45474 | N6: =EDATE($G6,N$7-1) -> 45505 | O6: =EDATE($G6,O$7-1) -> 45536 | ... BN6: =EDATE($G6,BN$7-1) -> 47088
E7: Assumptions | G7: 1 | H7: =G7+1 -> 2 | I7: =H7+1 -> 3 | J7: =I7+1 -> 4 | K7: =J7+1 -> 5 | L7: =K7+1 -> 6 | M7: =L7+1 -> 7 | N7: =M7+1 -> 8 | O7: =N7+1 -> 9 | ... BN7: =BM7+1 -> 60
A9: x | B9: x | C9: Summary Data
C11: Total Active Subscribers | G11: ='Subscribers & Revenue'!G42 -> 145 | H11: ='Subscribers & Revenue'!H42 -> 289 | I11: ='Subscribers & Revenue'!I42 -> 435 | J11: ='Subscribers & Revenue'!J42 -> 583 | K11: ='Subscribers & Revenue'!K42 -> 736 | L11: ='Subscribers & Revenue'!L42 -> 895 | M11: ='Subscribers & Revenue'!M42 -> 1062 | N11: ='Subscribers & Revenue'!N42 -> 1238 | ... BN11: ='Subscribers & Revenue'!BN42 -> 147786
C12: % growth | H12: =H11/G11-1 -> 0.99310345 | I12: =I11/H11-1 -> 0.50519031 | J12: =J11/I11-1 -> 0.34022989 | K12: =K11/J11-1 -> 0.26243568 | L12: =L11/K11-1 -> 0.21603261 | M12: =M11/L11-1 -> 0.18659218 | N12: =N11/M11-1 -> 0.16572505 | O12: =O11/N11-1 -> 0.15105008 | ... BN12: =BN11/BM11-1 -> 0.092421073
C18: New Monthly Subscribers | G18: ='Subscribers & Revenue'!G34 -> 90 | H18: ='Subscribers & Revenue'!H34 -> 99 | I18: ='Subscribers & Revenue'!I34 -> 109 | J18: ='Subscribers & Revenue'!J34 -> 120 | K18: ='Subscribers & Revenue'!K34 -> 132 | L18: ='Subscribers & Revenue'!L34 -> 145 | M18: ='Subscribers & Revenue'!M34 -> 160 | N18: ='Subscribers & Revenue'!N34 -> 176 | ... BN18: ='Subscribers & Revenue'!BN34 -> 24957
C19: New Annual Subscribers | G19: ='Subscribers & Revenue'!G35 -> 55 | H19: ='Subscribers & Revenue'!H35 -> 59 | I19: ='Subscribers & Revenue'!I35 -> 63 | J19: ='Subscribers & Revenue'!J35 -> 67 | K19: ='Subscribers & Revenue'!K35 -> 72 | L19: ='Subscribers & Revenue'!L35 -> 77 | M19: ='Subscribers & Revenue'!M35 -> 82 | N19: ='Subscribers & Revenue'!N35 -> 88 | ... BN19: ='Subscribers & Revenue'!BN35 -> 2982
C20: Total New Subscribers | G20: =SUM(G18:G19) -> 145 | H20: =SUM(H18:H19) -> 158 | I20: =SUM(I18:I19) -> 172 | J20: =SUM(J18:J19) -> 187 | K20: =SUM(K18:K19) -> 204 | L20: =SUM(L18:L19) -> 222 | M20: =SUM(M18:M19) -> 242 | N20: =SUM(N18:N19) -> 264 | ... BN20: =SUM(BN18:BN19) -> 27939
C21: % growth | H21: =H20/G20-1 -> 0.089655172 | I21: =I20/H20-1 -> 0.088607595 | J21: =J20/I20-1 -> 0.087209302 | K21: =K20/J20-1 -> 0.090909091 | L21: =L20/K20-1 -> 0.088235294 | M21: =M20/L20-1 -> 0.09009009 | N21: =N20/M20-1 -> 0.090909091 | O21: =O20/N20-1 -> 0.090909091 | ... BN21: =BN20/BM20-1 -> 0.096722277
C23: ARR | G23: ='Subscribers & Revenue'!G72 -> 50550 | H23: ='Subscribers & Revenue'!H72 -> 100620 | I23: ='Subscribers & Revenue'!I72 -> 151290 | J23: ='Subscribers & Revenue'!J72 -> 202560 | K23: ='Subscribers & Revenue'!K72 -> 255480 | L23: ='Subscribers & Revenue'!L72 -> 310410 | M23: ='Subscribers & Revenue'!M72 -> 368070 | N23: ='Subscribers & Revenue'!N72 -> 428790 | ... BN23: ='Subscribers & Revenue'!BN72 -> 50306640
C24: % growth | H24: =H23/G23-1 -> 0.99050445 | I24: =I23/H23-1 -> 0.50357782 | J24: =J23/I23-1 -> 0.33888558 | K24: =K23/J23-1 -> 0.26125592 | L24: =L23/K23-1 -> 0.21500705 | M24: =M23/L23-1 -> 0.18575432 | N24: =N23/M23-1 -> 0.16496862 | O24: =O23/N23-1 -> 0.15042328 | ... BN24: =BN23/BM23-1 -> 0.093451697
C26: Bookings | G26: ='Subscribers & Revenue'!G64 -> 20850 | H26: ='Subscribers & Revenue'!H64 -> 24720 | I26: ='Subscribers & Revenue'!I64 -> 28530 | J26: ='Subscribers & Revenue'!J64 -> 32280 | K26: ='Subscribers & Revenue'!K64 -> 36360 | L26: ='Subscribers & Revenue'!L64 -> 40470 | M26: ='Subscribers & Revenue'!M64 -> 44670 | N26: ='Subscribers & Revenue'!N64 -> 49290 | ... BN26: ='Subscribers & Revenue'!BN64 -> 4562370
C27: % growth | H27: =H26/G26-1 -> 0.18561151 | I27: =I26/H26-1 -> 0.15412621 | J27: =J26/I26-1 -> 0.13144059 | K27: =K26/J26-1 -> 0.12639405 | L27: =L26/K26-1 -> 0.1130363 | M27: =M26/L26-1 -> 0.10378058 | N27: =N26/M26-1 -> 0.10342512 | O27: =O26/N26-1 -> 0.096774194 | ... BN27: =BN26/BM26-1 -> 0.091557029
C29: Deferred Revenue (MRR) | G29: ='Subscribers & Revenue'!G76 -> -16637.5 | H29: ='Subscribers & Revenue'!H76 -> -16335 | I29: ='Subscribers & Revenue'!I76 -> -15922.5 | J29: ='Subscribers & Revenue'!J76 -> -15400 | K29: ='Subscribers & Revenue'!K76 -> -15070 | L29: ='Subscribers & Revenue'!L76 -> -14602.5 | M29: ='Subscribers & Revenue'!M76 -> -13997.5 | N29: ='Subscribers & Revenue'!N76 -> -13557.5 | ... BN29: ='Subscribers & Revenue'!BN76 -> -370150
A31: x | B31: x | C31: Income Statement
B33: x | C33: Revenue
C35: Revenue (MRR) | G35: ='Subscribers & Revenue'!G70 -> 4212.5 | H35: ='Subscribers & Revenue'!H70 -> 8385 | I35: ='Subscribers & Revenue'!I70 -> 12607.5 | J35: ='Subscribers & Revenue'!J70 -> 16880 | K35: ='Subscribers & Revenue'!K70 -> 21290 | L35: ='Subscribers & Revenue'!L70 -> 25867.5 | M35: ='Subscribers & Revenue'!M70 -> 30672.5 | N35: ='Subscribers & Revenue'!N70 -> 35732.5 | ... BN35: ='Subscribers & Revenue'!BN70 -> 4192220
C36: % growth | H36: =H35/G35-1 -> 0.99050445 | I36: =I35/H35-1 -> 0.50357782 | J36: =J35/I35-1 -> 0.33888558 | K36: =K35/J35-1 -> 0.26125592 | L36: =L35/K35-1 -> 0.21500705 | M36: =M35/L35-1 -> 0.18575432 | N36: =N35/M35-1 -> 0.16496862 | O36: =O35/N35-1 -> 0.15042328 | ... BN36: =BN35/BM35-1 -> 0.093451697
B38: x | C38: COGS
C40: Tech Stack Fees | G40: =-G$35*G41 -> -674 | H40: =-H$35*H41 -> -1341.6 | I40: =-I$35*I41 -> -2017.2 | J40: =-J$35*J41 -> -2700.8 | K40: =-K$35*K41 -> -3406.4 | L40: =-L$35*L41 -> -4138.8 | M40: =-M$35*M41 -> -4907.6 | N40: =-N$35*N41 -> -5717.2 | ... BN40: =-BN$35*BN41 -> -586910.8
C41: % revenue | E41: =Assumptions!$E$23 -> 0.16 | F41: =Assumptions!$E$24 -> -0.005 | G41: =E41 -> 0.16 | H41: =G41+$F41*IF(MONTH(H6)=1, 1, 0) -> 0.16 | I41: =H41+$F41*IF(MONTH(I6)=1, 1, 0) -> 0.16 | J41: =I41+$F41*IF(MONTH(J6)=1, 1, 0) -> 0.16 | K41: =J41+$F41*IF(MONTH(K6)=1, 1, 0) -> 0.16 | L41: =K41+$F41*IF(MONTH(L6)=1, 1, 0) -> 0.16 | M41: =L41+$F41*IF(MONTH(M6)=1, 1, 0) -> 0.16 | N41: =M41+$F41*IF(MONTH(N6)=1, 1, 0) -> 0.16 | O41: =N41+$F41*IF(MONTH(O6)=1, 1, 0) -> 0.16 | ... BN41: =BM41+$F41*IF(MONTH(BN6)=1, 1, 0) -> 0.14
C43: COGS | G43: =G40 -> -674 | H43: =H40 -> -1341.6 | I43: =I40 -> -2017.2 | J43: =J40 -> -2700.8 | K43: =K40 -> -3406.4 | L43: =L40 -> -4138.8 | M43: =M40 -> -4907.6 | N43: =N40 -> -5717.2 | ... BN43: =BN40 -> -586910.8
C45: Gross Profit | G45: =G43+G35 -> 3538.5 | H45: =H43+H35 -> 7043.4 | I45: =I43+I35 -> 10590.3 | J45: =J43+J35 -> 14179.2 | K45: =K43+K35 -> 17883.6 | L45: =L43+L35 -> 21728.7 | M45: =M43+M35 -> 25764.9 | N45: =N43+N35 -> 30015.3 | ... BN45: =BN43+BN35 -> 3605309.2
C46: % margin | G46: =G45/G$35 -> 0.84 | H46: =H45/H$35 -> 0.84 | I46: =I45/I$35 -> 0.84 | J46: =J45/J$35 -> 0.84 | K46: =K45/K$35 -> 0.84 | L46: =L45/L$35 -> 0.84 | M46: =M45/M$35 -> 0.84 | N46: =N45/N$35 -> 0.84 | ... BN46: =BN45/BN$35 -> 0.86
B48: x | C48: OPEX
B50: x | C50: Payroll & Headcount
C52: CEO Base Payroll | E52: =Assumptions!$E30 -> 150000 | G52: =$E52/12 -> 12500 | H52: =$E52/12 -> 12500 | I52: =$E52/12 -> 12500 | J52: =$E52/12 -> 12500 | K52: =$E52/12 -> 12500 | L52: =$E52/12 -> 12500 | M52: =$E52/12 -> 12500 | N52: =$E52/12 -> 12500 | ... BN52: =$E52/12 -> 12500
C53: CTO Base Payroll | E53: =Assumptions!$E31 -> 150000 | G53: =$E53/12 -> 12500 | H53: =$E53/12 -> 12500 | I53: =$E53/12 -> 12500 | J53: =$E53/12 -> 12500 | K53: =$E53/12 -> 12500 | L53: =$E53/12 -> 12500 | M53: =$E53/12 -> 12500 | N53: =$E53/12 -> 12500 | ... BN53: =$E53/12 -> 12500
C54: C-Suite Base Payroll | E54: =SUM(E52:E53) -> 300000 | G54: =SUM(G52:G53) -> 25000 | H54: =SUM(H52:H53) -> 25000 | I54: =SUM(I52:I53) -> 25000 | J54: =SUM(J52:J53) -> 25000 | K54: =SUM(K52:K53) -> 25000 | L54: =SUM(L52:L53) -> 25000 | M54: =SUM(M52:M53) -> 25000 | N54: =SUM(N52:N53) -> 25000 | ... BN54: =SUM(BN52:BN53) -> 25000
C56: Engineering Headcount | G56: =IF(MOD(MONTH(G$6)-1,3)=0,1,0)+F56 -> 1 | H56: =IF(MOD(MONTH(H$6)-1,3)=0,1,0)+G56 -> 1 | I56: =IF(MOD(MONTH(I$6)-1,3)=0,1,0)+H56 -> 1 | J56: =IF(MOD(MONTH(J$6)-1,3)=0,1,0)+I56 -> 2 | K56: =IF(MOD(MONTH(K$6)-1,3)=0,1,0)+J56 -> 2 | L56: =IF(MOD(MONTH(L$6)-1,3)=0,1,0)+K56 -> 2 | M56: =IF(MOD(MONTH(M$6)-1,3)=0,1,0)+L56 -> 3 | N56: =IF(MOD(MONTH(N$6)-1,3)=0,1,0)+M56 -> 3 | ... BN56: =IF(MOD(MONTH(BN$6)-1,3)=0,1,0)+BM56 -> 20
C57: Engineering Base Monthly Salary | E57: =Assumptions!$E$32 -> 180000 | G57: =$E57/12 -> 15000 | H57: =$E57/12 -> 15000 | I57: =$E57/12 -> 15000 | J57: =$E57/12 -> 15000 | K57: =$E57/12 -> 15000 | L57: =$E57/12 -> 15000 | M57: =$E57/12 -> 15000 | N57: =$E57/12 -> 15000 | ... BN57: =$E57/12 -> 15000
C58: Engineering Base Payroll | G58: =G57*G56 -> 15000 | H58: =H57*H56 -> 15000 | I58: =I57*I56 -> 15000 | J58: =J57*J56 -> 30000 | K58: =K57*K56 -> 30000 | L58: =L57*L56 -> 30000 | M58: =M57*M56 -> 45000 | N58: =N57*N56 -> 45000 | ... BN58: =BN57*BN56 -> 300000
C60: Customer Support Headcount | E60: =Assumptions!$E$34 -> 1000 | G60: =_xlfn.CEILING.MATH(G$11/$E60,1) -> 1 | H60: =_xlfn.CEILING.MATH(H$11/$E60,1) -> 1 | I60: =_xlfn.CEILING.MATH(I$11/$E60,1) -> 1 | J60: =_xlfn.CEILING.MATH(J$11/$E60,1) -> 1 | K60: =_xlfn.CEILING.MATH(K$11/$E60,1) -> 1 | L60: =_xlfn.CEILING.MATH(L$11/$E60,1) -> 1 | M60: =_xlfn.CEILING.MATH(M$11/$E60,1) -> 2 | N60: =_xlfn.CEILING.MATH(N$11/$E60,1) -> 2 | ... BN60: =_xlfn.CEILING.MATH(BN$11/$E60,1) -> 148
C61: Customer Support Base Monthly Salary | E61: =Assumptions!$E$33 -> 60000 | G61: =$E61/12 -> 5000 | H61: =$E61/12 -> 5000 | I61: =$E61/12 -> 5000 | J61: =$E61/12 -> 5000 | K61: =$E61/12 -> 5000 | L61: =$E61/12 -> 5000 | M61: =$E61/12 -> 5000 | N61: =$E61/12 -> 5000 | ... BN61: =$E61/12 -> 5000
C62: Customer Support Base Payrolll | G62: =G61*G60 -> 5000 | H62: =H61*H60 -> 5000 | I62: =I61*I60 -> 5000 | J62: =J61*J60 -> 5000 | K62: =K61*K60 -> 5000 | L62: =L61*L60 -> 5000 | M62: =M61*M60 -> 10000 | N62: =N61*N60 -> 10000 | ... BN62: =BN61*BN60 -> 740000
C64: Executive Headcount | E64: =Assumptions!$E$36 -> 500000 | G64: =_xlfn.FLOOR.MATH(G$23/$E64,1) -> 0 | H64: =_xlfn.FLOOR.MATH(H$23/$E64,1) -> 0 | I64: =_xlfn.FLOOR.MATH(I$23/$E64,1) -> 0 | J64: =_xlfn.FLOOR.MATH(J$23/$E64,1) -> 0 | K64: =_xlfn.FLOOR.MATH(K$23/$E64,1) -> 0 | L64: =_xlfn.FLOOR.MATH(L$23/$E64,1) -> 0 | M64: =_xlfn.FLOOR.MATH(M$23/$E64,1) -> 0 | N64: =_xlfn.FLOOR.MATH(N$23/$E64,1) -> 0 | ... BN64: =_xlfn.FLOOR.MATH(BN$23/$E64,1) -> 100
C65: Executive Monthly Salary | E65: =Assumptions!$E$35 -> 180000 | G65: =$E65/12 -> 15000 | H65: =$E65/12 -> 15000 | I65: =$E65/12 -> 15000 | J65: =$E65/12 -> 15000 | K65: =$E65/12 -> 15000 | L65: =$E65/12 -> 15000 | M65: =$E65/12 -> 15000 | N65: =$E65/12 -> 15000 | ... BN65: =$E65/12 -> 15000
C66: Executive Base Payroll | G66: =G65*G64 -> 0 | H66: =H65*H64 -> 0 | I66: =I65*I64 -> 0 | J66: =J65*J64 -> 0 | K66: =K65*K64 -> 0 | L66: =L65*L64 -> 0 | M66: =M65*M64 -> 0 | N66: =N65*N64 -> 0 | ... BN66: =BN65*BN64 -> 1500000
C68: Base Gross Payroll | G68: =SUM(G66,G62,G58,G54) -> 45000 | H68: =SUM(H66,H62,H58,H54) -> 45000 | I68: =SUM(I66,I62,I58,I54) -> 45000 | J68: =SUM(J66,J62,J58,J54) -> 60000 | K68: =SUM(K66,K62,K58,K54) -> 60000 | L68: =SUM(L66,L62,L58,L54) -> 60000 | M68: =SUM(M66,M62,M58,M54) -> 80000 | N68: =SUM(N66,N62,N58,N54) -> 80000 | ... BN68: =SUM(BN66,BN62,BN58,BN54) -> 2565000
C69: Yearly Base Salary Increase | E69: =Assumptions!$E$37 -> 0.08 | G69: =IF(G$7<=12,0,INDEX($G$70:$BN$70,MATCH(G$7-12,$G$7:$BN$7,0)))*$E69 -> 0 | H69: =IF(H$7<=12,0,INDEX($G$70:$BN$70,MATCH(H$7-12,$G$7:$BN$7,0)))*$E69 -> 0 | I69: =IF(I$7<=12,0,INDEX($G$70:$BN$70,MATCH(I$7-12,$G$7:$BN$7,0)))*$E69 -> 0 | J69: =IF(J$7<=12,0,INDEX($G$70:$BN$70,MATCH(J$7-12,$G$7:$BN$7,0)))*$E69 -> 0 | K69: =IF(K$7<=12,0,INDEX($G$70:$BN$70,MATCH(K$7-12,$G$7:$BN$7,0)))*$E69 -> 0 | L69: =IF(L$7<=12,0,INDEX($G$70:$BN$70,MATCH(L$7-12,$G$7:$BN$7,0)))*$E69 -> 0 | M69: =IF(M$7<=12,0,INDEX($G$70:$BN$70,MATCH(M$7-12,$G$7:$BN$7,0)))*$E69 -> 0 | N69: =IF(N$7<=12,0,INDEX($G$70:$BN$70,MATCH(N$7-12,$G$7:$BN$7,0)))*$E69 -> 0 | ... BN69: =IF(BN$7<=12,0,INDEX($G$70:$BN$70,MATCH(BN$7-12,$G$7:$BN$7,0)))*$E69 -> 85999.59
C70: Total Gross Payroll | G70: =SUM(G68:G69) -> 45000 | H70: =SUM(H68:H69) -> 45000 | I70: =SUM(I68:I69) -> 45000 | J70: =SUM(J68:J69) -> 60000 | K70: =SUM(K68:K69) -> 60000 | L70: =SUM(L68:L69) -> 60000 | M70: =SUM(M68:M69) -> 80000 | N70: =SUM(N68:N69) -> 80000 | ... BN70: =SUM(BN68:BN69) -> 2650999.6
C71: Fringe Costs of Gross Wages | E71: =Assumptions!E38 -> 0.2 | G71: =G70*$E71 -> 9000 | H71: =H70*$E71 -> 9000 | I71: =I70*$E71 -> 9000 | J71: =J70*$E71 -> 12000 | K71: =K70*$E71 -> 12000 | L71: =L70*$E71 -> 12000 | M71: =M70*$E71 -> 16000 | N71: =N70*$E71 -> 16000 | ... BN71: =BN70*$E71 -> 530199.92
C72: Total Base Payroll | G72: =SUM(G70:G71) -> 54000 | H72: =SUM(H70:H71) -> 54000 | I72: =SUM(I70:I71) -> 54000 | J72: =SUM(J70:J71) -> 72000 | K72: =SUM(K70:K71) -> 72000 | L72: =SUM(L70:L71) -> 72000 | M72: =SUM(M70:M71) -> 96000 | N72: =SUM(N70:N71) -> 96000 | ... BN72: =SUM(BN70:BN71) -> 3181199.5
C74: C-Suite Headcount | G74: =COUNT(G52:G53) -> 2 | H74: =COUNT(H52:H53) -> 2 | I74: =COUNT(I52:I53) -> 2 | J74: =COUNT(J52:J53) -> 2 | K74: =COUNT(K52:K53) -> 2 | L74: =COUNT(L52:L53) -> 2 | M74: =COUNT(M52:M53) -> 2 | N74: =COUNT(N52:N53) -> 2 | ... BN74: =COUNT(BN52:BN53) -> 2
C75: =C56 -> Engineering Headcount | G75: =G56 -> 1 | H75: =H56 -> 1 | I75: =I56 -> 1 | J75: =J56 -> 2 | K75: =K56 -> 2 | L75: =L56 -> 2 | M75: =M56 -> 3 | N75: =N56 -> 3 | ... BN75: =BN56 -> 20
C76: =C60 -> Customer Support Headcount | G76: =G60 -> 1 | H76: =H60 -> 1 | I76: =I60 -> 1 | J76: =J60 -> 1 | K76: =K60 -> 1 | L76: =L60 -> 1 | M76: =M60 -> 2 | N76: =N60 -> 2 | ... BN76: =BN60 -> 148
C77: =C64 -> Executive Headcount | G77: =G64 -> 0 | H77: =H64 -> 0 | I77: =I64 -> 0 | J77: =J64 -> 0 | K77: =K64 -> 0 | L77: =L64 -> 0 | M77: =M64 -> 0 | N77: =N64 -> 0 | ... BN77: =BN64 -> 100
C78: Total Headcount | G78: =SUM(G74:G77) -> 4 | H78: =SUM(H74:H77) -> 4 | I78: =SUM(I74:I77) -> 4 | J78: =SUM(J74:J77) -> 5 | K78: =SUM(K74:K77) -> 5 | L78: =SUM(L74:L77) -> 5 | M78: =SUM(M74:M77) -> 7 | N78: =SUM(N74:N77) -> 7 | ... BN78: =SUM(BN74:BN77) -> 270
B80: x | C80: General & Administrative
C82: G&A | G82: =G83*G$35 -> 210.625 | H82: =H83*H$35 -> 419.25 | I82: =I83*I$35 -> 630.375 | J82: =J83*J$35 -> 844 | K82: =K83*K$35 -> 1064.5 | L82: =L83*L$35 -> 1293.375 | M82: =M83*M$35 -> 1533.625 | N82: =N83*N$35 -> 1786.625 | ... BN82: =BN83*BN$35 -> 209611
C83: % revenue | E83: =Assumptions!$E$40 -> 0.05 | G83: =$E$83 -> 0.05 | H83: =$E$83 -> 0.05 | I83: =$E$83 -> 0.05 | J83: =$E$83 -> 0.05 | K83: =$E$83 -> 0.05 | L83: =$E$83 -> 0.05 | M83: =$E$83 -> 0.05 | N83: =$E$83 -> 0.05 | ... BN83: =$E$83 -> 0.05
B85: x | C85: Sales & Marketing
C87: =C18 -> New Monthly Subscribers | G87: =G18 -> 90 | H87: =H18 -> 99 | I87: =I18 -> 109 | J87: =J18 -> 120 | K87: =K18 -> 132 | L87: =L18 -> 145 | M87: =M18 -> 160 | N87: =N18 -> 176 | ... BN87: =BN18 -> 24957
C88: Monthly Subscriber CAC | E88: =Assumptions!E45 -> 100 | F88: =Assumptions!$E$46 -> 0.05 | G88: =$E88 -> 100 | H88: =G88-G88*IF(MOD(MONTH(H$6)-1,3)=0,1,0)*$F88 -> 100 | I88: =H88-H88*IF(MOD(MONTH(I$6)-1,3)=0,1,0)*$F88 -> 100 | J88: =I88-I88*IF(MOD(MONTH(J$6)-1,3)=0,1,0)*$F88 -> 95 | K88: =J88-J88*IF(MOD(MONTH(K$6)-1,3)=0,1,0)*$F88 -> 95 | L88: =K88-K88*IF(MOD(MONTH(L$6)-1,3)=0,1,0)*$F88 -> 95 | M88: =L88-L88*IF(MOD(MONTH(M$6)-1,3)=0,1,0)*$F88 -> 90.25 | N88: =M88-M88*IF(MOD(MONTH(N$6)-1,3)=0,1,0)*$F88 -> 90.25 | O88: =N88-N88*IF(MOD(MONTH(O$6)-1,3)=0,1,0)*$F88 -> 90.25 | ... BN88: =BM88-BM88*IF(MOD(MONTH(BN$6)-1,3)=0,1,0)*$F88 -> 37.73536
C89: Total Monthly Subscriber CAC | G89: =G87*G88 -> 9000 | H89: =H87*H88 -> 9900 | I89: =I87*I88 -> 10900 | J89: =J87*J88 -> 11400 | K89: =K87*K88 -> 12540 | L89: =L87*L88 -> 13775 | M89: =M87*M88 -> 14440 | N89: =N87*N88 -> 15884 | ... BN89: =BN87*BN88 -> 941761.39
C91: =C19 -> New Annual Subscribers | G91: =G19 -> 55 | H91: =H19 -> 59 | I91: =I19 -> 63 | J91: =J19 -> 67 | K91: =K19 -> 72 | L91: =L19 -> 77 | M91: =M19 -> 82 | N91: =N19 -> 88 | ... BN91: =BN19 -> 2982
C92: Annual Subscriber CAC | E92: =Assumptions!E44 -> 200 | F92: =Assumptions!E47 -> 0.03 | G92: =$E92 -> 200 | H92: =G92-G92*IF(MOD(MONTH(H$6)-1,3)=0,1,0)*$F92 -> 200 | I92: =H92-H92*IF(MOD(MONTH(I$6)-1,3)=0,1,0)*$F92 -> 200 | J92: =I92-I92*IF(MOD(MONTH(J$6)-1,3)=0,1,0)*$F92 -> 194 | K92: =J92-J92*IF(MOD(MONTH(K$6)-1,3)=0,1,0)*$F92 -> 194 | L92: =K92-K92*IF(MOD(MONTH(L$6)-1,3)=0,1,0)*$F92 -> 194 | M92: =L92-L92*IF(MOD(MONTH(M$6)-1,3)=0,1,0)*$F92 -> 188.18 | N92: =M92-M92*IF(MOD(MONTH(N$6)-1,3)=0,1,0)*$F92 -> 188.18 | O92: =N92-N92*IF(MOD(MONTH(O$6)-1,3)=0,1,0)*$F92 -> 188.18 | ... BN92: =BM92-BM92*IF(MOD(MONTH(BN$6)-1,3)=0,1,0)*$F92 -> 112.12254
C93: Total Annual Subscriber CAC | G93: =G91*G92 -> 11000 | H93: =H91*H92 -> 11800 | I93: =I91*I92 -> 12600 | J93: =J91*J92 -> 12998 | K93: =K91*K92 -> 13968 | L93: =L91*L92 -> 14938 | M93: =M91*M92 -> 15430.76 | N93: =N91*N92 -> 16559.84 | ... BN93: =BN91*BN92 -> 334349.43
C95: Customer Acquisition Costs (CAC) | G95: =G93+G89 -> 20000 | H95: =H93+H89 -> 21700 | I95: =I93+I89 -> 23500 | J95: =J93+J89 -> 24398 | K95: =K93+K89 -> 26508 | L95: =L93+L89 -> 28713 | M95: =M93+M89 -> 29870.76 | N95: =N93+N89 -> 32443.84 | ... BN95: =BN93+BN89 -> 1276110.8
B97: x | C97: Facilities | E97: Assumptions
C99: Offices | E99: =Assumptions!E52 -> 20 | G99: =IF(G$78<=$E99, 1, 2) -> 1 | H99: =IF(H$78<=$E99, 1, 2) -> 1 | I99: =IF(I$78<=$E99, 1, 2) -> 1 | J99: =IF(J$78<=$E99, 1, 2) -> 1 | K99: =IF(K$78<=$E99, 1, 2) -> 1 | L99: =IF(L$78<=$E99, 1, 2) -> 1 | M99: =IF(M$78<=$E99, 1, 2) -> 1 | N99: =IF(N$78<=$E99, 1, 2) -> 1 | ... BN99: =IF(BN$78<=$E99, 1, 2) -> 2
C100: Rent | E100: =Assumptions!E51 -> 10000 | G100: =G$99*$E100 -> 10000 | H100: =H$99*$E100 -> 10000 | I100: =I$99*$E100 -> 10000 | J100: =J$99*$E100 -> 10000 | K100: =K$99*$E100 -> 10000 | L100: =L$99*$E100 -> 10000 | M100: =M$99*$E100 -> 10000 | N100: =N$99*$E100 -> 10000 | ... BN100: =BN$99*$E100 -> 20000
C101: Utilities | E101: =Assumptions!$E$53 -> 4000 | G101: =G$99*$E101 -> 4000 | H101: =H$99*$E101 -> 4000 | I101: =I$99*$E101 -> 4000 | J101: =J$99*$E101 -> 4000 | K101: =K$99*$E101 -> 4000 | L101: =L$99*$E101 -> 4000 | M101: =M$99*$E101 -> 4000 | N101: =N$99*$E101 -> 4000 | ... BN101: =BN$99*$E101 -> 8000
C102: Total Facilities Costs | G102: =SUM(G100:G101) -> 14000 | H102: =SUM(H100:H101) -> 14000 | I102: =SUM(I100:I101) -> 14000 | J102: =SUM(J100:J101) -> 14000 | K102: =SUM(K100:K101) -> 14000 | L102: =SUM(L100:L101) -> 14000 | M102: =SUM(M100:M101) -> 14000 | N102: =SUM(N100:N101) -> 14000 | ... BN102: =SUM(BN100:BN101) -> 28000
B104: x | C104: Miscellaneous | E104: Assumptions
C106: Miscellaneous Expenses | G106: =G107*G$35 -> 210.625 | H106: =H107*H$35 -> 419.25 | I106: =I107*I$35 -> 630.375 | J106: =J107*J$35 -> 844 | K106: =K107*K$35 -> 1064.5 | L106: =L107*L$35 -> 1293.375 | M106: =M107*M$35 -> 1533.625 | N106: =N107*N$35 -> 1786.625 | ... BN106: =BN107*BN$35 -> 209611
C107: % revenue | E107: =Assumptions!$E$55 -> 0.05 | G107: =$E107 -> 0.05 | H107: =$E107 -> 0.05 | I107: =$E107 -> 0.05 | J107: =$E107 -> 0.05 | K107: =$E107 -> 0.05 | L107: =$E107 -> 0.05 | M107: =$E107 -> 0.05 | N107: =$E107 -> 0.05 | ... BN107: =$E107 -> 0.05
C109: Payroll | G109: =-G72 -> -54000 | H109: =-H72 -> -54000 | I109: =-I72 -> -54000 | J109: =-J72 -> -72000 | K109: =-K72 -> -72000 | L109: =-L72 -> -72000 | M109: =-M72 -> -96000 | N109: =-N72 -> -96000 | ... BN109: =-BN72 -> -3181199.5
C110: G&A | G110: =-G82 -> -210.625 | H110: =-H82 -> -419.25 | I110: =-I82 -> -630.375 | J110: =-J82 -> -844 | K110: =-K82 -> -1064.5 | L110: =-L82 -> -1293.375 | M110: =-M82 -> -1533.625 | N110: =-N82 -> -1786.625 | ... BN110: =-BN82 -> -209611
C111: S&M | G111: =-G95 -> -20000 | H111: =-H95 -> -21700 | I111: =-I95 -> -23500 | J111: =-J95 -> -24398 | K111: =-K95 -> -26508 | L111: =-L95 -> -28713 | M111: =-M95 -> -29870.76 | N111: =-N95 -> -32443.84 | ... BN111: =-BN95 -> -1276110.8
C112: Facilities | G112: =-G102 -> -14000 | H112: =-H102 -> -14000 | I112: =-I102 -> -14000 | J112: =-J102 -> -14000 | K112: =-K102 -> -14000 | L112: =-L102 -> -14000 | M112: =-M102 -> -14000 | N112: =-N102 -> -14000 | ... BN112: =-BN102 -> -28000
C113: Miscellaneous | G113: =-G106 -> -210.625 | H113: =-H106 -> -419.25 | I113: =-I106 -> -630.375 | J113: =-J106 -> -844 | K113: =-K106 -> -1064.5 | L113: =-L106 -> -1293.375 | M113: =-M106 -> -1533.625 | N113: =-N106 -> -1786.625 | ... BN113: =-BN106 -> -209611
C114: OPEX | G114: =SUM(G109:G113) -> -88421.25 | H114: =SUM(H109:H113) -> -90538.5 | I114: =SUM(I109:I113) -> -92760.75 | J114: =SUM(J109:J113) -> -112086 | K114: =SUM(K109:K113) -> -114637 | L114: =SUM(L109:L113) -> -117299.75 | M114: =SUM(M109:M113) -> -142938.01 | N114: =SUM(N109:N113) -> -146017.09 | ... BN114: =SUM(BN109:BN113) -> -4904532.3
C116: Operating Profit | G116: =G45+G114 -> -84882.75 | H116: =H45+H114 -> -83495.1 | I116: =I45+I114 -> -82170.45 | J116: =J45+J114 -> -97906.8 | K116: =K45+K114 -> -96753.4 | L116: =L45+L114 -> -95571.05 | M116: =M45+M114 -> -117173.11 | N116: =N45+N114 -> -116001.79 | ... BN116: =BN45+BN114 -> -1299223.1
C117: % margin | G117: =G116/G$35 -> -20.150208 | H117: =H116/H$35 -> -9.9576744 | I117: =I116/I$35 -> -6.5175848 | J117: =J116/J$35 -> -5.8001659 | K117: =K116/K$35 -> -4.5445467 | L117: =L116/L$35 -> -3.6946381 | M117: =M116/M$35 -> -3.8201356 | N117: =N116/N$35 -> -3.2463945 | ... BN117: =BN116/BN$35 -> -0.30991292
B119: x | C119: Taxes
C121: Net Operating Losses
C123: Beginning Balance | G123: =F125 -> 0 | H123: =G125 -> 84882.75 | I123: =H125 -> 168377.85 | J123: =I125 -> 250548.3 | K123: =J125 -> 348455.1 | L123: =K125 -> 445208.5 | M123: =L125 -> 540779.55 | N123: =M125 -> 657952.66 | ... BN123: =BM125 -> 26817602
C124: NOL Utilized | G124: =-IF(G116<0,0,MIN(G123, G116)) -> 0 | H124: =-IF(H116<0,0,MIN(H123, H116)) -> 0 | I124: =-IF(I116<0,0,MIN(I123, I116)) -> 0 | J124: =-IF(J116<0,0,MIN(J123, J116)) -> 0 | K124: =-IF(K116<0,0,MIN(K123, K116)) -> 0 | L124: =-IF(L116<0,0,MIN(L123, L116)) -> 0 | M124: =-IF(M116<0,0,MIN(M123, M116)) -> 0 | N124: =-IF(N116<0,0,MIN(N123, N116)) -> 0 | ... BN124: =-IF(BN116<0,0,MIN(BN123, BN116)) -> 0
C125: Ending Balance | G125: =G123-MIN(G116,0)+G124 -> 84882.75 | H125: =H123-MIN(H116,0)+H124 -> 168377.85 | I125: =I123-MIN(I116,0)+I124 -> 250548.3 | J125: =J123-MIN(J116,0)+J124 -> 348455.1 | K125: =K123-MIN(K116,0)+K124 -> 445208.5 | L125: =L123-MIN(L116,0)+L124 -> 540779.55 | M125: =M123-MIN(M116,0)+M124 -> 657952.66 | N125: =N123-MIN(N116,0)+N124 -> 773954.45 | ... BN125: =BN123-MIN(BN116,0)+BN124 -> 28116825
C127: Taxable Income | G127: =IF(G116<0,0, G116+G124) -> 0 | H127: =IF(H116<0,0, H116+H124) -> 0 | I127: =IF(I116<0,0, I116+I124) -> 0 | J127: =IF(J116<0,0, J116+J124) -> 0 | K127: =IF(K116<0,0, K116+K124) -> 0 | L127: =IF(L116<0,0, L116+L124) -> 0 | M127: =IF(M116<0,0, M116+M124) -> 0 | N127: =IF(N116<0,0, N116+N124) -> 0 | ... BN127: =IF(BN116<0,0, BN116+BN124) -> 0
C128: Taxes (%) | E128: =Assumptions!E60 -> 0.21 | G128: =$E128 -> 0.21 | H128: =$E128 -> 0.21 | I128: =$E128 -> 0.21 | J128: =$E128 -> 0.21 | K128: =$E128 -> 0.21 | L128: =$E128 -> 0.21 | M128: =$E128 -> 0.21 | N128: =$E128 -> 0.21 | ... BN128: =$E128 -> 0.21
C129: Tax Expense | G129: =-G127*G128 -> 0 | H129: =-H127*H128 -> 0 | I129: =-I127*I128 -> 0 | J129: =-J127*J128 -> 0 | K129: =-K127*K128 -> 0 | L129: =-L127*L128 -> 0 | M129: =-M127*M128 -> 0 | N129: =-N127*N128 -> 0 | ... BN129: =-BN127*BN128 -> 0
B131: x | C131: Net Income | G131: =G116+G129 -> -84882.75 | H131: =H116+H129 -> -83495.1 | I131: =I116+I129 -> -82170.45 | J131: =J116+J129 -> -97906.8 | K131: =K116+K129 -> -96753.4 | L131: =L116+L129 -> -95571.05 | M131: =M116+M129 -> -117173.11 | N131: =N116+N129 -> -116001.79 | ... BN131: =BN116+BN129 -> -1299223.1
A133: x | B133: x | C133: Balance Sheet
B135: x | C135: Assets
C137: Cash & Cash Equivalents | G137: =G213 -> 937624.17 | H137: =H213 -> 876277.75 | I137: =I213 -> 815913.15 | J137: =J213 -> 738346.57 | K137: =K213 -> 662543.17 | L137: =L213 -> 587677.95 | M137: =M213 -> 489068.66 | N137: =N213 -> 393067.43 | ... BN137: =BN213 -> 1000000
C139: Revenue (ARR) | G139: =G$23 -> 50550 | H139: =H$23 -> 100620 | I139: =I$23 -> 151290 | J139: =J$23 -> 202560 | K139: =K$23 -> 255480 | L139: =L$23 -> 310410 | M139: =M$23 -> 368070 | N139: =N$23 -> 428790 | ... BN139: =BN$23 -> 50306640
C140: DSO | E140: =Assumptions!E65 -> 5 | G140: =$E140 -> 5 | H140: =$E140 -> 5 | I140: =$E140 -> 5 | J140: =$E140 -> 5 | K140: =$E140 -> 5 | L140: =$E140 -> 5 | M140: =$E140 -> 5 | N140: =$E140 -> 5 | ... BN140: =$E140 -> 5
C141: Accounts Receivable | G141: =G139*(G140/360) -> 702.08333 | H141: =H139*(H140/360) -> 1397.5 | I141: =I139*(I140/360) -> 2101.25 | J141: =J139*(J140/360) -> 2813.3333 | K141: =K139*(K140/360) -> 3548.3333 | L141: =L139*(L140/360) -> 4311.25 | M141: =M139*(M140/360) -> 5112.0833 | N141: =N139*(N140/360) -> 5955.4167 | ... BN141: =BN139*(BN140/360) -> 698703.33
C143: Total Assets | G143: =SUM(G137, G141) -> 938326.25 | H143: =SUM(H137, H141) -> 877675.25 | I143: =SUM(I137, I141) -> 818014.4 | J143: =SUM(J137, J141) -> 741159.9 | K143: =SUM(K137, K141) -> 666091.5 | L143: =SUM(L137, L141) -> 591989.2 | M143: =SUM(M137, M141) -> 494180.74 | N143: =SUM(N137, N141) -> 399022.85 | ... BN143: =SUM(BN137, BN141) -> 1698703.3
B145: x | C145: Liabilities
C147: Revenue (ARR) | G147: =G$23 -> 50550 | H147: =H$23 -> 100620 | I147: =I$23 -> 151290 | J147: =J$23 -> 202560 | K147: =K$23 -> 255480 | L147: =L$23 -> 310410 | M147: =M$23 -> 368070 | N147: =N$23 -> 428790 | ... BN147: =BN$23 -> 50306640
C148: % ARR | E148: =Assumptions!E66 -> 0.05 | G148: =$E148 -> 0.05 | H148: =$E148 -> 0.05 | I148: =$E148 -> 0.05 | J148: =$E148 -> 0.05 | K148: =$E148 -> 0.05 | L148: =$E148 -> 0.05 | M148: =$E148 -> 0.05 | N148: =$E148 -> 0.05 | ... BN148: =$E148 -> 0.05
C149: Accounts Payable | G149: =G147*G148 -> 2527.5 | H149: =H147*H148 -> 5031 | I149: =I147*I148 -> 7564.5 | J149: =J147*J148 -> 10128 | K149: =K147*K148 -> 12774 | L149: =L147*L148 -> 15520.5 | M149: =M147*M148 -> 18403.5 | N149: =N147*N148 -> 21439.5 | ... BN149: =BN147*BN148 -> 2515332
C151: Revenue (ARR) | G151: =G$23 -> 50550 | H151: =H$23 -> 100620 | I151: =I$23 -> 151290 | J151: =J$23 -> 202560 | K151: =K$23 -> 255480 | L151: =L$23 -> 310410 | M151: =M$23 -> 368070 | N151: =N$23 -> 428790 | ... BN151: =BN$23 -> 50306640
C152: % ARR | E152: =Assumptions!$E$67 -> 0.08 | F152: =Assumptions!E68 -> -0.005 | G152: =E152 -> 0.08 | H152: =IF(MOD(MONTH(H$6)-1,3)=0,1,0)*$F152+G152 -> 0.08 | I152: =IF(MOD(MONTH(I$6)-1,3)=0,1,0)*$F152+H152 -> 0.08 | J152: =IF(MOD(MONTH(J$6)-1,3)=0,1,0)*$F152+I152 -> 0.075 | K152: =IF(MOD(MONTH(K$6)-1,3)=0,1,0)*$F152+J152 -> 0.075 | L152: =IF(MOD(MONTH(L$6)-1,3)=0,1,0)*$F152+K152 -> 0.075 | M152: =IF(MOD(MONTH(M$6)-1,3)=0,1,0)*$F152+L152 -> 0.07 | N152: =IF(MOD(MONTH(N$6)-1,3)=0,1,0)*$F152+M152 -> 0.07 | O152: =IF(MOD(MONTH(O$6)-1,3)=0,1,0)*$F152+N152 -> 0.07 | ... BN152: =IF(MOD(MONTH(BN$6)-1,3)=0,1,0)*$F152+BM152 -> -0.015
C153: Other Current Liabilities | G153: =G151*G152 -> 4044 | H153: =H151*H152 -> 8049.6 | I153: =I151*I152 -> 12103.2 | J153: =J151*J152 -> 15192 | K153: =K151*K152 -> 19161 | L153: =L151*L152 -> 23280.75 | M153: =M151*M152 -> 25764.9 | N153: =N151*N152 -> 30015.3 | ... BN153: =BN151*BN152 -> -754599.6
...

Sheet Subscribers & Revenue
G4: =YEAR(G6) -> 2024 | H4: =YEAR(H6) -> 2024 | I4: =YEAR(I6) -> 2024 | J4: =YEAR(J6) -> 2024 | K4: =YEAR(K6) -> 2024 | L4: =YEAR(L6) -> 2024 | M4: =YEAR(M6) -> 2024 | N4: =YEAR(N6) -> 2024 | ... BN4: =YEAR(BN6) -> 2028
G5: =ROUNDUP(MONTH(G6)/3,0) -> 1 | H5: =ROUNDUP(MONTH(H6)/3,0) -> 1 | I5: =ROUNDUP(MONTH(I6)/3,0) -> 1 | J5: =ROUNDUP(MONTH(J6)/3,0) -> 2 | K5: =ROUNDUP(MONTH(K6)/3,0) -> 2 | L5: =ROUNDUP(MONTH(L6)/3,0) -> 2 | M5: =ROUNDUP(MONTH(M6)/3,0) -> 3 | N5: =ROUNDUP(MONTH(N6)/3,0) -> 3 | ... BN5: =ROUNDUP(MONTH(BN6)/3,0) -> 4
G6: 45292 | H6: =EDATE($G6,H$7-1) -> 45323 | I6: =EDATE($G6,I$7-1) -> 45352 | J6: =EDATE($G6,J$7-1) -> 45383 | K6: =EDATE($G6,K$7-1) -> 45413 | L6: =EDATE($G6,L$7-1) -> 45444 | M6: =EDATE($G6,M$7-1) -> 45474 | N6: =EDATE($G6,N$7-1) -> 45505 | O6: =EDATE($G6,O$7-1) -> 45536 | ... BN6: =EDATE($G6,BN$7-1) -> 47088
E7: Assumptions | G7: 1 | H7: =G7+1 -> 2 | I7: =H7+1 -> 3 | J7: =I7+1 -> 4 | K7: =J7+1 -> 5 | L7: =K7+1 -> 6 | M7: =L7+1 -> 7 | N7: =M7+1 -> 8 | O7: =N7+1 -> 9 | ... BN7: =BM7+1 -> 60
A9: x | B9: x | C9: Subscribers
B11: x | C11: Monthly Subscribers
C13: New Monthly Subscribers | E13: =Assumptions!E7 -> 90 | G13: =E$13 -> 90 | H13: =ROUND(G13*(1+H14),0) -> 99 | I13: =ROUND(H13*(1+I14),0) -> 109 | J13: =ROUND(I13*(1+J14),0) -> 120 | K13: =ROUND(J13*(1+K14),0) -> 132 | L13: =ROUND(K13*(1+L14),0) -> 145 | M13: =ROUND(L13*(1+M14),0) -> 160 | N13: =ROUND(M13*(1+N14),0) -> 176 | O13: =ROUND(N13*(1+O14),0) -> 194 | ... BN13: =ROUND(BM13*(1+BN14),0) -> 24957
C14: % growth | E14: =Assumptions!E8 -> 0.1 | H14: =$E$14 -> 0.1 | I14: =$E$14 -> 0.1 | J14: =$E$14 -> 0.1 | K14: =$E$14 -> 0.1 | L14: =$E$14 -> 0.1 | M14: =$E$14 -> 0.1 | N14: =$E$14 -> 0.1 | O14: =$E$14 -> 0.1 | ... BN14: =$E$14 -> 0.1
C16: Previous Month Active Subscribers | G16: =F19 -> 0 | H16: =G19 -> 90 | I16: =H19 -> 175 | J16: =I19 -> 258 | K16: =J19 -> 339 | L16: =K19 -> 420 | M16: =L19 -> 502 | N16: =M19 -> 587 | ... BN16: =BM19 -> 99822
C17: (+) New Subscribers | G17: =G13 -> 90 | H17: =H13 -> 99 | I17: =I13 -> 109 | J17: =J13 -> 120 | K17: =K13 -> 132 | L17: =L13 -> 145 | M17: =M13 -> 160 | N17: =N13 -> 176 | ... BN17: =BN13 -> 24957
C18: (–) Churned Subscribers | E18: =Assumptions!E9 -> 0.85 | G18: =-ROUND(G16*(1-$E$18),0) -> 0 | H18: =-ROUND(H16*(1-$E$18),0) -> -14 | I18: =-ROUND(I16*(1-$E$18),0) -> -26 | J18: =-ROUND(J16*(1-$E$18),0) -> -39 | K18: =-ROUND(K16*(1-$E$18),0) -> -51 | L18: =-ROUND(L16*(1-$E$18),0) -> -63 | M18: =-ROUND(M16*(1-$E$18),0) -> -75 | N18: =-ROUND(N16*(1-$E$18),0) -> -88 | ... BN18: =-ROUND(BN16*(1-$E$18),0) -> -14973
C19: Active Monthly Subscribers | G19: =SUM(G16:G18) -> 90 | H19: =SUM(H16:H18) -> 175 | I19: =SUM(I16:I18) -> 258 | J19: =SUM(J16:J18) -> 339 | K19: =SUM(K16:K18) -> 420 | L19: =SUM(L16:L18) -> 502 | M19: =SUM(M16:M18) -> 587 | N19: =SUM(N16:N18) -> 675 | ... BN19: =SUM(BN16:BN18) -> 109806
B21: x | C21: Annual Subscribers
C23: New Annual Subscribers | E23: =Assumptions!E14 -> 55 | G23: =E$23 -> 55 | H23: =ROUND(G23*(1+H24),0) -> 59 | I23: =ROUND(H23*(1+I24),0) -> 63 | J23: =ROUND(I23*(1+J24),0) -> 67 | K23: =ROUND(J23*(1+K24),0) -> 72 | L23: =ROUND(K23*(1+L24),0) -> 77 | M23: =ROUND(L23*(1+M24),0) -> 82 | N23: =ROUND(M23*(1+N24),0) -> 88 | O23: =ROUND(N23*(1+O24),0) -> 94 | ... BN23: =ROUND(BM23*(1+BN24),0) -> 2982
C24: % growth | E24: =Assumptions!E15 -> 0.07 | H24: =$E$24 -> 0.07 | I24: =$E$24 -> 0.07 | J24: =$E$24 -> 0.07 | K24: =$E$24 -> 0.07 | L24: =$E$24 -> 0.07 | M24: =$E$24 -> 0.07 | N24: =$E$24 -> 0.07 | O24: =$E$24 -> 0.07 | ... BN24: =$E$24 -> 0.07
C26: Previous Month Active Subscribers | G26: =F29 -> 0 | H26: =G29 -> 55 | I26: =H29 -> 114 | J26: =I29 -> 177 | K26: =J29 -> 244 | L26: =K29 -> 316 | M26: =L29 -> 393 | N26: =M29 -> 475 | ... BN26: =BM29 -> 35461
C27: (+) New Subscribers | G27: =G23 -> 55 | H27: =H23 -> 59 | I27: =I23 -> 63 | J27: =J23 -> 67 | K27: =K23 -> 72 | L27: =L23 -> 77 | M27: =M23 -> 82 | N27: =N23 -> 88 | ... BN27: =BN23 -> 2982
C28: (–) Churned Subscribers | E28: =Assumptions!E16 -> 0.65 | G28: 0 | H28: 0 | I28: 0 | J28: 0 | K28: 0 | L28: 0 | M28: 0 | N28: 0 | O28: 0 | P28: 0 | Q28: 0 | R28: 0 | S28: =-ROUND(G$23*(1-$E$28),0) -> -19 | T28: =-ROUND(H$23*(1-$E$28),0) -> -21 | U28: =-ROUND(I$23*(1-$E$28),0) -> -22 | V28: =-ROUND(J$23*(1-$E$28),0) -> -23 | W28: =-ROUND(K$23*(1-$E$28),0) -> -25 | X28: =-ROUND(L$23*(1-$E$28),0) -> -27 | Y28: =-ROUND(M$23*(1-$E$28),0) -> -29 | Z28: =-ROUND(N$23*(1-$E$28),0) -> -31 | ... BN28: =-ROUND(BB$23*(1-$E$28),0) -> -463
C29: Active Annual Subscribers | G29: =SUM(G26:G28) -> 55 | H29: =SUM(H26:H28) -> 114 | I29: =SUM(I26:I28) -> 177 | J29: =SUM(J26:J28) -> 244 | K29: =SUM(K26:K28) -> 316 | L29: =SUM(L26:L28) -> 393 | M29: =SUM(M26:M28) -> 475 | N29: =SUM(N26:N28) -> 563 | ... BN29: =SUM(BN26:BN28) -> 37980
C30: Memo: Renewals | G30: =IF(G28=0, 0, 1) -> 0 | H30: =IF(H28=0, 0, 1) -> 0 | I30: =IF(I28=0, 0, 1) -> 0 | J30: =IF(J28=0, 0, 1) -> 0 | K30: =IF(K28=0, 0, 1) -> 0 | L30: =IF(L28=0, 0, 1) -> 0 | M30: =IF(M28=0, 0, 1) -> 0 | N30: =IF(N28=0, 0, 1) -> 0 | ... R30: =IF(R28=0, 0, 1) -> 0 | S30: =ROUND(G$23*$E$28,0) -> 36 | T30: =ROUND(H$23*$E$28,0) -> 38 | U30: =ROUND(I$23*$E$28,0) -> 41 | V30: =ROUND(J$23*$E$28,0) -> 44 | W30: =ROUND(K$23*$E$28,0) -> 47 | X30: =ROUND(L$23*$E$28,0) -> 50 | Y30: =ROUND(M$23*$E$28,0) -> 53 | Z30: =ROUND(N$23*$E$28,0) -> 57 | ... BN30: =ROUND(BB$23*$E$28,0) -> 861
B32: x | C32: New Subscribers
C34: =C13 -> New Monthly Subscribers | G34: =G13 -> 90 | H34: =H13 -> 99 | I34: =I13 -> 109 | J34: =J13 -> 120 | K34: =K13 -> 132 | L34: =L13 -> 145 | M34: =M13 -> 160 | N34: =N13 -> 176 | ... BN34: =BN13 -> 24957
C35: =C23 -> New Annual Subscribers | G35: =G23 -> 55 | H35: =H23 -> 59 | I35: =I23 -> 63 | J35: =J23 -> 67 | K35: =K23 -> 72 | L35: =L23 -> 77 | M35: =M23 -> 82 | N35: =N23 -> 88 | ... BN35: =BN23 -> 2982
C36: New Subscribers | G36: =SUM(G34:G35) -> 145 | H36: =SUM(H34:H35) -> 158 | I36: =SUM(I34:I35) -> 172 | J36: =SUM(J34:J35) -> 187 | K36: =SUM(K34:K35) -> 204 | L36: =SUM(L34:L35) -> 222 | M36: =SUM(M34:M35) -> 242 | N36: =SUM(N34:N35) -> 264 | ... BN36: =SUM(BN34:BN35) -> 27939
B38: x | C38: Total Subscribers
C40: =C19 -> Active Monthly Subscribers | G40: =G19 -> 90 | H40: =H19 -> 175 | I40: =I19 -> 258 | J40: =J19 -> 339 | K40: =K19 -> 420 | L40: =L19 -> 502 | M40: =M19 -> 587 | N40: =N19 -> 675 | ... BN40: =BN19 -> 109806
C41: =C29 -> Active Annual Subscribers | G41: =G29 -> 55 | H41: =H29 -> 114 | I41: =I29 -> 177 | J41: =J29 -> 244 | K41: =K29 -> 316 | L41: =L29 -> 393 | M41: =M29 -> 475 | N41: =N29 -> 563 | ... BN41: =BN29 -> 37980
C42: Total Active Subscribers | G42: =SUM(G40:G41) -> 145 | H42: =SUM(H40:H41) -> 289 | I42: =SUM(I40:I41) -> 435 | J42: =SUM(J40:J41) -> 583 | K42: =SUM(K40:K41) -> 736 | L42: =SUM(L40:L41) -> 895 | M42: =SUM(M40:M41) -> 1062 | N42: =SUM(N40:N41) -> 1238 | ... BN42: =SUM(BN40:BN41) -> 147786
A44: x | B44: x | C44: Bookings
B46: x | C46: Monthly Subscribers
C48: =C19 -> Active Monthly Subscribers | G48: =G19 -> 90 | H48: =H19 -> 175 | I48: =I19 -> 258 | J48: =J19 -> 339 | K48: =K19 -> 420 | L48: =L19 -> 502 | M48: =M19 -> 587 | N48: =N19 -> 675 | ... BN48: =BN19 -> 109806
C49: Monthly Plan Price / month | E49: =Assumptions!E10 -> 30 | G49: =$E$49 -> 30 | H49: =$E$49 -> 30 | I49: =$E$49 -> 30 | J49: =$E$49 -> 30 | K49: =$E$49 -> 30 | L49: =$E$49 -> 30 | M49: =$E$49 -> 30 | N49: =$E$49 -> 30 | ... BN49: =$E$49 -> 30
C50: Monthly Plan Bookings | G50: =G48*G49 -> 2700 | H50: =H48*H49 -> 5250 | I50: =I48*I49 -> 7740 | J50: =J48*J49 -> 10170 | K50: =K48*K49 -> 12600 | L50: =L48*L49 -> 15060 | M50: =M48*M49 -> 17610 | N50: =N48*N49 -> 20250 | ... BN50: =BN48*BN49 -> 3294180
B52: x | C52: Annual Subscribers
C54: =C23 -> New Annual Subscribers | G54: =G23 -> 55 | H54: =H23 -> 59 | I54: =I23 -> 63 | J54: =J23 -> 67 | K54: =K23 -> 72 | L54: =L23 -> 77 | M54: =M23 -> 82 | N54: =N23 -> 88 | ... BN54: =BN23 -> 2982
C55: (+) Renewals | G55: =G30 -> 0 | H55: =H30 -> 0 | I55: =I30 -> 0 | J55: =J30 -> 0 | K55: =K30 -> 0 | L55: =L30 -> 0 | M55: =M30 -> 0 | N55: =N30 -> 0 | ... BN55: =BN30 -> 861
C56: Total Annual Subscribers | G56: =SUM(G54:G55) -> 55 | H56: =SUM(H54:H55) -> 59 | I56: =SUM(I54:I55) -> 63 | J56: =SUM(J54:J55) -> 67 | K56: =SUM(K54:K55) -> 72 | L56: =SUM(L54:L55) -> 77 | M56: =SUM(M54:M55) -> 82 | N56: =SUM(N54:N55) -> 88 | ... BN56: =SUM(BN54:BN55) -> 3843
C57: Annual Plan Price / year | E57: =Assumptions!E17 -> 330 | G57: =$E$57 -> 330 | H57: =$E$57 -> 330 | I57: =$E$57 -> 330 | J57: =$E$57 -> 330 | K57: =$E$57 -> 330 | L57: =$E$57 -> 330 | M57: =$E$57 -> 330 | N57: =$E$57 -> 330 | ... BN57: =$E$57 -> 330
C58: Annual Plan Bookings | G58: =G56*G57 -> 18150 | H58: =H56*H57 -> 19470 | I58: =I56*I57 -> 20790 | J58: =J56*J57 -> 22110 | K58: =K56*K57 -> 23760 | L58: =L56*L57 -> 25410 | M58: =M56*M57 -> 27060 | N58: =N56*N57 -> 29040 | ... BN58: =BN56*BN57 -> 1268190
B60: x | C60: Total Bookings
C62: =C50 -> Monthly Plan Bookings | G62: =G50 -> 2700 | H62: =H50 -> 5250 | I62: =I50 -> 7740 | J62: =J50 -> 10170 | K62: =K50 -> 12600 | L62: =L50 -> 15060 | M62: =M50 -> 17610 | N62: =N50 -> 20250 | ... BN62: =BN50 -> 3294180
C63: =C58 -> Annual Plan Bookings | G63: =G58 -> 18150 | H63: =H58 -> 19470 | I63: =I58 -> 20790 | J63: =J58 -> 22110 | K63: =K58 -> 23760 | L63: =L58 -> 25410 | M63: =M58 -> 27060 | N63: =N58 -> 29040 | ... BN63: =BN58 -> 1268190
C64: Total Bookings | G64: =SUM(G62:G63) -> 20850 | H64: =SUM(H62:H63) -> 24720 | I64: =SUM(I62:I63) -> 28530 | J64: =SUM(J62:J63) -> 32280 | K64: =SUM(K62:K63) -> 36360 | L64: =SUM(L62:L63) -> 40470 | M64: =SUM(M62:M63) -> 44670 | N64: =SUM(N62:N63) -> 49290 | ... BN64: =SUM(BN62:BN63) -> 4562370
A66: x | B66: x | C66: Revenue
C68: Monthly Plan Revenue | G68: =G50 -> 2700 | H68: =H50 -> 5250 | I68: =I50 -> 7740 | J68: =J50 -> 10170 | K68: =K50 -> 12600 | L68: =L50 -> 15060 | M68: =M50 -> 17610 | N68: =N50 -> 20250 | ... BN68: =BN50 -> 3294180
C69: Annual Plan Monthly Revenue | G69: =SUM($G58:G58)/12 -> 1512.5 | H69: =SUM($G58:H58)/12 -> 3135 | I69: =SUM($G58:I58)/12 -> 4867.5 | J69: =SUM($G58:J58)/12 -> 6710 | K69: =SUM($G58:K58)/12 -> 8690 | L69: =SUM($G58:L58)/12 -> 10807.5 | M69: =SUM($G58:M58)/12 -> 13062.5 | N69: =SUM($G58:N58)/12 -> 15482.5 | ... Q69: =SUM($G58:Q58)/12 -> 23815 | R69: =SUM(G58:R58)/12 -> 27005 | S69: =SUM(H58:S58)/12 -> 29892.5 | T69: =SUM(I58:T58)/12 -> 32972.5 | U69: =SUM(J58:U58)/12 -> 36272.5 | V69: =SUM(K58:V58)/12 -> 39820 | W69: =SUM(L58:W58)/12 -> 43615 | X69: =SUM(M58:X58)/12 -> 47657.5 | Y69: =SUM(N58:Y58)/12 -> 51975 | ... BN69: =SUM(BC58:BN58)/12 -> 898040
C70: MRR | G70: =SUM(G68:G69) -> 4212.5 | H70: =SUM(H68:H69) -> 8385 | I70: =SUM(I68:I69) -> 12607.5 | J70: =SUM(J68:J69) -> 16880 | K70: =SUM(K68:K69) -> 21290 | L70: =SUM(L68:L69) -> 25867.5 | M70: =SUM(M68:M69) -> 30672.5 | N70: =SUM(N68:N69) -> 35732.5 | ... BN70: =SUM(BN68:BN69) -> 4192220
C72: ARR | G72: =G70*12 -> 50550 | H72: =H70*12 -> 100620 | I72: =I70*12 -> 151290 | J72: =J70*12 -> 202560 | K72: =K70*12 -> 255480 | L72: =L70*12 -> 310410 | M72: =M70*12 -> 368070 | N72: =N70*12 -> 428790 | ... BN72: =BN70*12 -> 50306640
C74: =C70 -> MRR | G74: =G70 -> 4212.5 | H74: =H70 -> 8385 | I74: =I70 -> 12607.5 | J74: =J70 -> 16880 | K74: =K70 -> 21290 | L74: =L70 -> 25867.5 | M74: =M70 -> 30672.5 | N74: =N70 -> 35732.5 | ... BN74: =BN70 -> 4192220
C75: ="(–) " &C64 -> (–) Total Bookings | G75: =-G64 -> -20850 | H75: =-H64 -> -24720 | I75: =-I64 -> -28530 | J75: =-J64 -> -32280 | K75: =-K64 -> -36360 | L75: =-L64 -> -40470 | M75: =-M64 -> -44670 | N75: =-N64 -> -49290 | ... BN75: =-BN64 -> -4562370
C76: Deferred Revenue | G76: =SUM(G74:G75) -> -16637.5 | H76: =SUM(H74:H75) -> -16335 | I76: =SUM(I74:I75) -> -15922.5 | J76: =SUM(J74:J75) -> -15400 | K76: =SUM(K74:K75) -> -15070 | L76: =SUM(L74:L75) -> -14602.5 | M76: =SUM(M74:M75) -> -13997.5 | N76: =SUM(N74:N75) -> -13557.5 | ... BN76: =SUM(BN74:BN75) -> -370150
C77: Balance | G77: =G76 -> -16637.5 | H77: =H76+G77 -> -32972.5 | I77: =I76+H77 -> -48895 | J77: =J76+I77 -> -64295 | K77: =K76+J77 -> -79365 | L77: =L76+K77 -> -93967.5 | M77: =M76+L77 -> -107965 | N77: =N76+M77 -> -121522.5 | O77: =O76+N77 -> -134475 | ... BN77: =BN76+BM77 -> -5655732.5
